{"bucketQuery": "bucket('npc_id').select('page_name','page_name_sub','id').limit(500).offset(9000).run()", "bucket": [{"page_name_sub": "Leagues Tutor (Raging Echoes League)", "id": ["316"], "page_name": "Leagues Tutor (Raging Echoes League)"}, {"page_name_sub": "Sir Burrus#Adopted", "id": ["14165"], "page_name": "Sir Burrus"}, {"page_name_sub": "Sir Burrus#Dressed", "id": ["hist14154", "hist14183"], "page_name": "Sir Burrus"}, {"page_name_sub": "Sir Burrus#Wild", "id": ["hist12593"], "page_name": "Sir Burrus"}, {"page_name_sub": "Archibald (dog)#Adopted", "id": ["14167"], "page_name": "Archibald (dog)"}, {"page_name_sub": "Archibald (dog)#Dressed", "id": ["hist14156", "hist14184"], "page_name": "Archibald (dog)"}, {"page_name_sub": "Archibald (dog)#Wild", "id": ["hist12596"], "page_name": "Archibald (dog)"}, {"page_name_sub": "Sadie#Adopted", "id": ["14163"], "page_name": "Sadie"}, {"page_name_sub": "Sadie#Dressed", "id": ["hist14152"], "page_name": "Sadie"}, {"page_name_sub": "Sadie#Wild", "id": ["hist10476"], "page_name": "Sadie"}, {"page_name_sub": "Kimba#Adopted", "id": ["14171"], "page_name": "Kimba"}, {"page_name_sub": "Kimba#Cutscene", "id": ["hist14186"], "page_name": "Kimba"}, {"page_name_sub": "Kimba#Dressed", "id": ["hist14160"], "page_name": "Kimba"}, {"page_name_sub": "Kimba#Wild", "id": ["hist14150"], "page_name": "Kimba"}, {"page_name_sub": "Duke (dog)#Adopted", "id": ["14169", " hist14168"], "page_name": "Duke (dog)"}, {"page_name_sub": "Duke (dog)#Dressed", "id": ["hist14158"], "page_name": "Duke (dog)"}, {"page_name_sub": "Duke (dog)#Wild", "id": ["hist14148"], "page_name": "Duke (dog)"}, {"page_name_sub": "Cecilia (2024 Christmas event)#1", "id": ["hist14173"], "page_name": "Cecilia (2024 Christmas event)"}, {"page_name_sub": "Cecilia (2024 Christmas event)#2", "id": ["hist14187"], "page_name": "Cecilia (2024 Christmas event)"}, {"page_name_sub": "Gertrude (2024 Christmas event)#1", "id": ["hist14175"], "page_name": "Gertrude (2024 Christmas event)"}, {"page_name_sub": "Gertrude (2024 Christmas event)#2", "id": ["hist14188"], "page_name": "Gertrude (2024 Christmas event)"}, {"page_name_sub": "Hairdresser (2024 Christmas event)#1", "id": ["hist14177"], "page_name": "Hairdresser (2024 Christmas event)"}, {"page_name_sub": "Hairdresser (2024 Christmas event)#2", "id": ["hist14189"], "page_name": "Hairdresser (2024 Christmas event)"}, {"page_name_sub": "Sir Amik Varze (2024 Christmas event)#1", "id": ["hist14179"], "page_name": "Sir Amik Varze (2024 Christmas event)"}, {"page_name_sub": "Sir Amik Varze (2024 Christmas event)#2", "id": ["hist14190"], "page_name": "Sir Amik Varze (2024 Christmas event)"}, {"page_name_sub": "Sarah (2024 Christmas event)#1", "id": ["hist14181"], "page_name": "Sarah (2024 Christmas event)"}, {"page_name_sub": "Sarah (2024 Christmas event)#2", "id": ["hist14191"], "page_name": "Sarah (2024 Christmas event)"}, {"page_name_sub": "Party Pete (2024 Christmas event)", "id": ["hist14192"], "page_name": "Party Pete (2024 Christmas event)"}, {"page_name_sub": "Charlie the Tramp (2024 Christmas event)", "id": ["hist14193"], "page_name": "Charlie the Tramp (2024 Christmas event)"}, {"page_name_sub": "Evil Chicken (Nightmare Zone)#Hard Mode", "id": ["6306"], "page_name": "Evil Chicken (Nightmare Zone)"}, {"page_name_sub": "Evil Chicken (Nightmare Zone)#Normal Mode", "id": ["6367"], "page_name": "Evil Chicken (Nightmare Zone)"}, {"page_name_sub": "Mummy (Klenter's Pyramid)#1", "id": ["949"], "page_name": "Mummy (Klenter's Pyramid)"}, {"page_name_sub": "Mummy (Klenter's Pyramid)#3", "id": ["951"], "page_name": "Mummy (Klenter's Pyramid)"}, {"page_name_sub": "Mummy (Klenter's Pyramid)#2", "id": ["950"], "page_name": "Mummy (Klenter's Pyramid)"}, {"page_name_sub": "Mummy (Klenter's Pyramid)#5", "id": ["953"], "page_name": "Mummy (Klenter's Pyramid)"}, {"page_name_sub": "Mummy (Klenter's Pyramid)#4", "id": ["952"], "page_name": "Mummy (Klenter's Pyramid)"}, {"page_name_sub": "Mummy (Pyramid Plunder)#1", "id": ["7658"], "page_name": "Mummy (Pyramid Plunder)"}, {"page_name_sub": "Mummy (Pyramid Plunder)#3", "id": ["7661"], "page_name": "Mummy (Pyramid Plunder)"}, {"page_name_sub": "Mummy (Pyramid Plunder)#2", "id": ["7659"], "page_name": "Mummy (Pyramid Plunder)"}, {"page_name_sub": "Mummy (Pyramid Plunder)#5", "id": ["7662"], "page_name": "Mummy (Pyramid Plunder)"}, {"page_name_sub": "Mummy (Pyramid Plunder)#4", "id": ["7660"], "page_name": "Mummy (Pyramid Plunder)"}, {"page_name_sub": "Ice Troll King (Nightmare Zone)#Hard Mode", "id": ["6294"], "page_name": "Ice Troll King (Nightmare Zone)"}, {"page_name_sub": "Ice Troll King (Nightmare Zone)#Normal Mode", "id": ["6356"], "page_name": "Ice Troll King (Nightmare Zone)"}, {"page_name_sub": "Mummy (Ancient Pyramid sarcophagus)#Level 98", "id": ["724"], "page_name": "Mummy (Ancient Pyramid sarcophagus)"}, {"page_name_sub": "Mummy (Ancient Pyramid sarcophagus)#Level 96", "id": ["717"], "page_name": "Mummy (Ancient Pyramid sarcophagus)"}, {"page_name_sub": "Mummy ashes#1", "id": ["718"], "page_name": "Mummy ashes"}, {"page_name_sub": "Mummy ashes#2", "id": ["719"], "page_name": "Mummy ashes"}, {"page_name_sub": "Basilisk (The Fremennik Exiles)#1", "id": ["9283", "9284"], "page_name": "Basilisk (The Fremennik Exiles)"}, {"page_name_sub": "Basilisk (The Fremennik Exiles)#2", "id": ["9285", "9286"], "page_name": "Basilisk (The Fremennik Exiles)"}, {"page_name_sub": "Turoth (unused)#Level 86", "id": ["426"], "page_name": "Turoth (unused)"}, {"page_name_sub": "Turoth (unused)#Level 88 (white)", "id": ["431"], "page_name": "Turoth (unused)"}, {"page_name_sub": "Turoth (unused)#Level 88 (brown)", "id": ["432"], "page_name": "Turoth (unused)"}, {"page_name_sub": "General Wartface (historical)", "id": ["676", "1192", "1195"], "page_name": "General Wartface (historical)"}, {"page_name_sub": "Doom of Mokhaiotl#Delve 2", "id": ["14707"], "page_name": "Doom of Mokhaiotl"}, {"page_name_sub": "Doom of Mokhaiotl#Delve 4", "id": ["14707"], "page_name": "Doom of Mokhaiotl"}, {"page_name_sub": "Doom of Mokhaiotl#Delve 8", "id": ["14707"], "page_name": "Doom of Mokhaiotl"}, {"page_name_sub": "Doom of Mokhaiotl#Delve 3", "id": ["14707"], "page_name": "Doom of Mokhaiotl"}, {"page_name_sub": "Doom of Mokhaiotl#Delve 7", "id": ["14707"], "page_name": "Doom of Mokhaiotl"}, {"page_name_sub": "Doom of Mokhaiotl#Delve 1", "id": ["14707"], "page_name": "Doom of Mokhaiotl"}, {"page_name_sub": "Doom of Mokhaiotl#Delve 5", "id": ["14707"], "page_name": "Doom of Mokhaiotl"}, {"page_name_sub": "Doom of Mokhaiotl#Deep Delve", "id": ["14707"], "page_name": "Doom of Mokhaiotl"}, {"page_name_sub": "Doom of Mokhaiotl#Delve 6", "id": ["14707"], "page_name": "Doom of Mokhaiotl"}, {"page_name_sub": "Doom of Mokhaiotl#Delve 2", "id": ["14708"], "page_name": "Doom of Mokhaiotl"}, {"page_name_sub": "Doom of Mokhaiotl#Delve 4", "id": ["14708"], "page_name": "Doom of Mokhaiotl"}, {"page_name_sub": "Doom of Mokhaiotl#Delve 8", "id": ["14708"], "page_name": "Doom of Mokhaiotl"}, {"page_name_sub": "Doom of Mokhaiotl#Delve 3", "id": ["14708"], "page_name": "Doom of Mokhaiotl"}, {"page_name_sub": "Doom of Mokhaiotl#Delve 7", "id": ["14708"], "page_name": "Doom of Mokhaiotl"}, {"page_name_sub": "Doom of Mokhaiotl#Delve 1", "id": ["14708"], "page_name": "Doom of Mokhaiotl"}, {"page_name_sub": "Doom of Mokhaiotl#Delve 5", "id": ["14708"], "page_name": "Doom of Mokhaiotl"}, {"page_name_sub": "Doom of Mokhaiotl#Deep Delve", "id": ["14708"], "page_name": "Doom of Mokhaiotl"}, {"page_name_sub": "Doom of Mokhaiotl#Delve 6", "id": ["14708"], "page_name": "Doom of Mokhaiotl"}, {"page_name_sub": "Doom of Mokhaiotl#Delve 7", "id": ["14709"], "page_name": "Doom of Mokhaiotl"}, {"page_name_sub": "Doom of Mokhaiotl#Delve 5", "id": ["14709"], "page_name": "Doom of Mokhaiotl"}, {"page_name_sub": "Doom of Mokhaiotl#Delve 8", "id": ["14709"], "page_name": "Doom of Mokhaiotl"}, {"page_name_sub": "Doom of Mokhaiotl#Deep Delve", "id": ["14709"], "page_name": "Doom of Mokhaiotl"}, {"page_name_sub": "Doom of Mokhaiotl#Delve 6", "id": ["14709"], "page_name": "Doom of Mokhaiotl"}, {"page_name_sub": "Leagues Tutor (Twisted League)#Normal world", "id": ["hist316"], "page_name": "Leagues Tutor (Twisted League)"}, {"page_name_sub": "Leagues Tutor (Twisted League)#Leagues world", "id": ["hist315"], "page_name": "Leagues Tutor (Twisted League)"}, {"page_name_sub": "Web (Verzik Vitur)", "id": ["8376"], "page_name": "Web (Verzik Vitur)"}, {"page_name_sub": "Hobgoblin (The Slug Menace)", "id": ["4805"], "page_name": "Hobgoblin (The Slug Menace)"}, {"page_name_sub": "Zombie (Stronghold of Security)#Level 30, 1", "id": ["2501"], "page_name": "Zombie (Stronghold of Security)"}, {"page_name_sub": "Zombie (Stronghold of Security)#Level 30, 3", "id": ["2503"], "page_name": "Zombie (Stronghold of Security)"}, {"page_name_sub": "Zombie (Stronghold of Security)#Level 30, 2", "id": ["2502"], "page_name": "Zombie (Stronghold of Security)"}, {"page_name_sub": "Zombie (Stronghold of Security)#Level 44, 3", "id": ["2506"], "page_name": "Zombie (Stronghold of Security)"}, {"page_name_sub": "Zombie (Stronghold of Security)#Level 44, 2", "id": ["2505"], "page_name": "Zombie (Stronghold of Security)"}, {"page_name_sub": "Zombie (Stronghold of Security)#Level 44, 1", "id": ["2504"], "page_name": "Zombie (Stronghold of Security)"}, {"page_name_sub": "Zombie (Stronghold of Security)#Level 53, 1", "id": ["2507"], "page_name": "Zombie (Stronghold of Security)"}, {"page_name_sub": "Zombie (Stronghold of Security)#Level 53, 2", "id": ["2508"], "page_name": "Zombie (Stronghold of Security)"}, {"page_name_sub": "Zombie (Stronghold of Security)#Level 53, 3", "id": ["2509"], "page_name": "Zombie (Stronghold of Security)"}, {"page_name_sub": "Zombie (Wilderness)#Level 18, 4", "id": ["48"], "page_name": "Zombie (Wilderness)"}, {"page_name_sub": "Zombie (Wilderness)#Level 18, 5", "id": ["6596"], "page_name": "Zombie (Wilderness)"}, {"page_name_sub": "Zombie (Wilderness)#Level 18, 2", "id": ["46"], "page_name": "Zombie (Wilderness)"}, {"page_name_sub": "Zombie (Wilderness)#Level 18, 1", "id": ["45"], "page_name": "Zombie (Wilderness)"}, {"page_name_sub": "Zombie (Wilderness)#Level 18, 6", "id": ["6597"], "page_name": "Zombie (Wilderness)"}, {"page_name_sub": "Zombie (Wilderness)#Level 18, 7", "id": ["6598"], "page_name": "Zombie (Wilderness)"}, {"page_name_sub": "Zombie (Wilderness)#Level 18, 3", "id": ["47"], "page_name": "Zombie (Wilderness)"}, {"page_name_sub": "Zombie (Wilderness)#Level 24, 2", "id": ["60"], "page_name": "Zombie (Wilderness)"}, {"page_name_sub": "Zombie (Wilderness)#Level 24, 3", "id": ["61"], "page_name": "Zombie (Wilderness)"}, {"page_name_sub": "Zombie (Wilderness)#Level 24, 5", "id": ["63"], "page_name": "Zombie (Wilderness)"}, {"page_name_sub": "Zombie (Wilderness)#Level 24, 1", "id": ["59"], "page_name": "Zombie (Wilderness)"}, {"page_name_sub": "Zombie (Wilderness)#Level 24, 4", "id": ["62"], "page_name": "Zombie (Wilderness)"}, {"page_name_sub": "Zombie (Kourend)#Level 70", "id": ["7485"], "page_name": "Zombie (Kourend)"}, {"page_name_sub": "Zombie (Kourend)#Level 72", "id": ["7488"], "page_name": "Zombie (Kourend)"}, {"page_name_sub": "Zombie (Kourend)#Level 56", "id": ["7486"], "page_name": "Zombie (Kourend)"}, {"page_name_sub": "Zombie (Kourend)#Level 76", "id": ["7487"], "page_name": "Zombie (Kourend)"}, {"page_name_sub": "Eldric the Ice King", "id": ["14147"], "page_name": "Eldric the Ice King"}, {"page_name_sub": "Eldric the Ice King", "id": ["14149"], "page_name": "Eldric the Ice King"}, {"page_name_sub": "Branda the Fire Queen", "id": ["12596"], "page_name": "Branda the Fire Queen"}, {"page_name_sub": "Branda the Fire Queen", "id": ["14148"], "page_name": "Branda the Fire Queen"}, {"page_name_sub": "Cat (Mess)", "id": ["395"], "page_name": "Cat (Mess)"}, {"page_name_sub": "Starflower (scenery)#Shoot", "id": ["1856"], "page_name": "Starflower (scenery)"}, {"page_name_sub": "Starflower (scenery)#Bloom", "id": ["1857"], "page_name": "Starflower (scenery)"}, {"page_name_sub": "Fire elemental (Royal Titans)", "id": ["14150"], "page_name": "Fire elemental (Royal Titans)"}, {"page_name_sub": "Bran#Ric", "id": ["12592", "12595"], "page_name": "Bran"}, {"page_name_sub": "Bran#Bran", "id": ["10476", "12593"], "page_name": "Bran"}, {"page_name_sub": "Ice elemental (Royal Titans)", "id": ["14151"], "page_name": "Ice elemental (Royal Titans)"}, {"page_name_sub": "Icicles (Royal Titans)", "id": ["14153"], "page_name": "Icicles (Royal Titans)"}, {"page_name_sub": "Fire (Royal Titans)", "id": ["14152"], "page_name": "Fire (Royal Titans)"}, {"page_name_sub": "Greater demon (The Scar)", "id": ["12387"], "page_name": "Greater demon (The Scar)"}, {"page_name_sub": "Black demon (The Scar)", "id": ["12385"], "page_name": "Black demon (The Scar)"}, {"page_name_sub": "Deviled Dave", "id": ["hist14157"], "page_name": "Deviled Dave"}, {"page_name_sub": "Khazard Guard (Arena escort)", "id": ["1212"], "page_name": "Khazard Guard (Arena escort)"}, {"page_name_sub": "Khazard Guard (Off duty)", "id": ["1210"], "page_name": "Khazard Guard (Off duty)"}, {"page_name_sub": "Meaty Aura Logist", "id": ["15154"], "page_name": "Meaty Aura Logist"}, {"page_name_sub": "Rum-dashed Ralph", "id": ["15095", "15096", "15097"], "page_name": "Rum-dashed Ralph"}, {"page_name_sub": "Shipwright Sam", "id": ["15363"], "page_name": "Shipwright Sam"}, {"page_name_sub": "Port Wizard Perrie", "id": ["15378"], "page_name": "Port Wizard Perrie"}, {"page_name_sub": "Anne#Cutscene", "id": ["14965", "14966"], "page_name": "Anne"}, {"page_name_sub": "Anne#Talk-to", "id": ["14964"], "page_name": "Anne"}, {"page_name_sub": "Will#Cutscene", "id": ["14960", "14961"], "page_name": "Will"}, {"page_name_sub": "Will#Talk-to", "id": ["14959"], "page_name": "Will"}, {"page_name_sub": "Great white shark", "id": ["15200"], "page_name": "Great white shark"}, {"page_name_sub": "Great white shark", "id": ["15201"], "page_name": "Great white shark"}, {"page_name_sub": "'Squawking' Steve Beanie#Trade", "id": ["14969"], "page_name": "'Squawking' Steve Beanie"}, {"page_name_sub": "'Squawking' Steve Beanie#Talk-to", "id": ["14968"], "page_name": "'Squawking' Steve Beanie"}, {"page_name_sub": "Junior Jim#After quest", "id": ["14975"], "page_name": "Junior Jim"}, {"page_name_sub": "Junior Jim#Limbo", "id": ["15238"], "page_name": "Junior Jim"}, {"page_name_sub": "Junior Jim#During quest", "id": ["14974"], "page_name": "Junior Jim"}, {"page_name_sub": "Old Grog", "id": ["14977"], "page_name": "Old Grog"}, {"page_name_sub": "Faaid", "id": ["14230"], "page_name": "Faaid"}, {"page_name_sub": "Charles Charlington II", "id": ["14953"], "page_name": "Charles Charlington II"}, {"page_name_sub": "Draven Quillshade", "id": ["14954"], "page_name": "Draven Quillshade"}, {"page_name_sub": "Fenric Hollowspire", "id": ["14955"], "page_name": "Fenric Hollowspire"}, {"page_name_sub": "Henderson", "id": ["14866"], "page_name": "Henderson"}, {"page_name_sub": "One Eyed Rosalee", "id": ["14867"], "page_name": "One Eyed Rosalee"}, {"page_name_sub": "Captain Dawson", "id": ["14868"], "page_name": "Captain Dawson"}, {"page_name_sub": "Fiora", "id": ["14869"], "page_name": "Fiora"}, {"page_name_sub": "Parleying Preston", "id": ["14870"], "page_name": "Parleying Preston"}, {"page_name_sub": "Brass Hand Harry", "id": ["14872"], "page_name": "Brass Hand Harry"}, {"page_name_sub": "Reggle, Master Coral Farmer", "id": ["beta14220"], "page_name": "Reggle, Master Coral Farmer"}, {"page_name_sub": "Gabba, Apprentice Coral Farmer", "id": ["beta14221"], "page_name": "Gabba, Apprentice Coral Farmer"}, {"page_name_sub": "Shipwright Sally", "id": ["15364"], "page_name": "Shipwright Sally"}, {"page_name_sub": "Shipwright Sophie", "id": ["15365"], "page_name": "Shipwright Sophie"}, {"page_name_sub": "Shipwright Steve", "id": ["15366"], "page_name": "Shipwright Steve"}, {"page_name_sub": "Shipwright Sarah", "id": ["15367"], "page_name": "Shipwright Sarah"}, {"page_name_sub": "Shipwright Spencer", "id": ["15369"], "page_name": "Shipwright Spencer"}, {"page_name_sub": "Shipwright Sennia", "id": ["15370"], "page_name": "Shipwright Sennia"}, {"page_name_sub": "Shipwright Seth", "id": ["beta14234"], "page_name": "Shipwright Seth"}, {"page_name_sub": "Shipwright Sigrun", "id": ["15371"], "page_name": "Shipwright Sigrun"}, {"page_name_sub": "Shipwright Silas", "id": ["15372"], "page_name": "Shipwright Silas"}, {"page_name_sub": "Port Wizard Peter", "id": ["15379"], "page_name": "Port Wizard Peter"}, {"page_name_sub": "Port Wizard Petra", "id": ["15380"], "page_name": "Port Wizard Petra"}, {"page_name_sub": "Famished shark", "id": ["beta14455"], "page_name": "Famished shark"}, {"page_name_sub": "Famished shark", "id": ["beta14456"], "page_name": "Famished shark"}, {"page_name_sub": "Crandor shark", "id": ["beta14457"], "page_name": "Crandor shark"}, {"page_name_sub": "Crandor shark", "id": ["beta14458"], "page_name": "Crandor shark"}, {"page_name_sub": "Karamjan tiger shark", "id": ["beta14459"], "page_name": "Karamjan tiger shark"}, {"page_name_sub": "Karamjan tiger shark", "id": ["beta14460"], "page_name": "Karamjan tiger shark"}, {"page_name_sub": "Large reef shark", "id": ["beta15047"], "page_name": "Large reef shark"}, {"page_name_sub": "Large reef shark", "id": ["beta15048"], "page_name": "Large reef shark"}, {"page_name_sub": "Baby sea kraken", "id": ["beta14465"], "page_name": "Baby sea kraken"}, {"page_name_sub": "Baby sea kraken", "id": ["beta14466"], "page_name": "Baby sea kraken"}, {"page_name_sub": "Pygmy kraken", "id": ["15206"], "page_name": "Pygmy kraken"}, {"page_name_sub": "Pygmy kraken", "id": ["15207"], "page_name": "Pygmy kraken"}, {"page_name_sub": "Sea monodon", "id": ["beta14471"], "page_name": "Sea monodon"}, {"page_name_sub": "Sea monodon", "id": ["beta14472"], "page_name": "Sea monodon"}, {"page_name_sub": "Catherby monodon", "id": ["beta15059"], "page_name": "Catherby monodon"}, {"page_name_sub": "Catherby monodon", "id": ["beta15060"], "page_name": "Catherby monodon"}, {"page_name_sub": "Ogre monodon", "id": ["beta15061"], "page_name": "Ogre monodon"}, {"page_name_sub": "Ogre monodon", "id": ["beta15062"], "page_name": "Ogre monodon"}, {"page_name_sub": "Kharazi monodon", "id": ["beta15063"], "page_name": "Kharazi monodon"}, {"page_name_sub": "Kharazi monodon", "id": ["beta15064"], "page_name": "Kharazi monodon"}, {"page_name_sub": "Sea hawk", "id": ["beta14479"], "page_name": "Sea hawk"}, {"page_name_sub": "Sea hawk", "id": ["beta14480"], "page_name": "Sea hawk"}, {"page_name_sub": "Whale", "id": ["beta15077"], "page_name": "Whale"}, {"page_name_sub": "Whale", "id": ["beta15078"], "page_name": "Whale"}, {"page_name_sub": "Baby leviathan", "id": ["beta14489"], "page_name": "Baby leviathan"}, {"page_name_sub": "Baby leviathan", "id": ["beta14490"], "page_name": "Baby leviathan"}, {"page_name_sub": "Spawn sharhai", "id": ["beta15081"], "page_name": "Spawn sharhai"}, {"page_name_sub": "Spawn sharhai", "id": ["beta15082"], "page_name": "Spawn sharhai"}, {"page_name_sub": "Victoria Kebbit-Monkfish#Dive", "id": ["15155"], "page_name": "Victoria Kebbit-Monkfish"}, {"page_name_sub": "Victoria Kebbit-Monkfish#Talk-to", "id": ["14945", "14947"], "page_name": "Victoria Kebbit-Monkfish"}, {"page_name_sub": "Drink troll", "id": ["15164"], "page_name": "Drink troll"}, {"page_name_sub": "Gracefish Shoal", "id": ["beta14315", "beta14316"], "page_name": "Gracefish Shoal"}, {"page_name_sub": "Crew Registrar#During quest", "id": ["15245"], "page_name": "Crew Registrar"}, {"page_name_sub": "Crew Registrar#After quest", "id": ["15246"], "page_name": "Crew Registrar"}, {"page_name_sub": "Jobless Jim#Cargo 2", "id": ["15259"], "page_name": "Jobless Jim"}, {"page_name_sub": "Jobless Jim#Cargo 3", "id": ["15260"], "page_name": "Jobless Jim"}, {"page_name_sub": "Jobless Jim#Dock", "id": ["15254"], "page_name": "Jobless Jim"}, {"page_name_sub": "Jobless Jim#Command", "id": ["15256"], "page_name": "Jobless Jim"}, {"page_name_sub": "Jobless Jim#Talk-to", "id": ["15253"], "page_name": "Jobless Jim"}, {"page_name_sub": "Jobless Jim#Cargo 1", "id": ["15258"], "page_name": "Jobless Jim"}, {"page_name_sub": "Jobless Jim#No-op", "id": ["15257"], "page_name": "Jobless Jim"}, {"page_name_sub": "Bronze eagle", "id": ["15412"], "page_name": "Bronze eagle"}, {"page_name_sub": "Jumbo Jim", "id": ["15239"], "page_name": "Jumbo Jim"}, {"page_name_sub": "Ribs (The Pandemonium)", "id": ["14971"], "page_name": "Ribs (The Pandemonium)"}, {"page_name_sub": "Current duck#Moving", "id": ["15152"], "page_name": "Current duck"}, {"page_name_sub": "Current duck#Collect", "id": ["15153"], "page_name": "Current duck"}, {"page_name_sub": "Port master#Sunset Coast", "id": ["15475"], "page_name": "Port master"}, {"page_name_sub": "Port master#Piscatoris Fishing Colony", "id": ["15488"], "page_name": "Port master"}, {"page_name_sub": "Port master#Rellekka", "id": ["15471"], "page_name": "Port master"}, {"page_name_sub": "Port master#The Summer Shore", "id": ["15476"], "page_name": "Port master"}, {"page_name_sub": "Port master#Port Piscarilius", "id": ["15469"], "page_name": "Port master"}, {"page_name_sub": "Port master#Hosidius", "id": ["15473"], "page_name": "Port master"}, {"page_name_sub": "Port master#The Pandemonium", "id": ["15461"], "page_name": "Port master"}, {"page_name_sub": "Port master#Ruins of Unkah", "id": ["15468"], "page_name": "Port master"}, {"page_name_sub": "Port master#Cairn Isle", "id": ["15474"], "page_name": "Port master"}, {"page_name_sub": "Port master#Corsair Cove", "id": ["15467"], "page_name": "Port master"}, {"page_name_sub": "Port master#Deepfin Point", "id": ["15484"], "page_name": "Port master"}, {"page_name_sub": "Port master#Mos Le'Harmless", "id": ["15481"], "page_name": "Port master"}, {"page_name_sub": "Port master#Red Rock", "id": ["15480"], "page_name": "Port master"}, {"page_name_sub": "Port master#Port Khazard", "id": ["15466"], "page_name": "Port master"}, {"page_name_sub": "Port master#Musa Point", "id": ["15460"], "page_name": "Port master"}, {"page_name_sub": "Port master#Catherby", "id": ["15462"], "page_name": "Port master"}, {"page_name_sub": "Port master#Aldarin", "id": ["15477"], "page_name": "Port master"}, {"page_name_sub": "Port master#Jatizso", "id": ["15485"], "page_name": "Port master"}, {"page_name_sub": "Port master#Ardougne", "id": ["15464"], "page_name": "Port master"}, {"page_name_sub": "Port master#Brimhaven", "id": ["15465"], "page_name": "Port master"}, {"page_name_sub": "Port master#Port Sarim", "id": ["15459"], "page_name": "Port master"}, {"page_name_sub": "Port master#Port Tyras", "id": ["15483"], "page_name": "Port master"}, {"page_name_sub": "Port master#Etceteria", "id": ["15482"], "page_name": "Port master"}, {"page_name_sub": "Port master#Port Roberts", "id": ["15479"], "page_name": "Port master"}, {"page_name_sub": "Port master#Void Knights' Outpost", "id": ["15478"], "page_name": "Port master"}, {"page_name_sub": "Port master#Civitas illa Fortis", "id": ["15470"], "page_name": "Port master"}, {"page_name_sub": "Port master#Prifddinas", "id": ["15487"], "page_name": "Port master"}, {"page_name_sub": "Port master#Lunar Isle", "id": ["15489"], "page_name": "Port master"}, {"page_name_sub": "Port master#Neitiznot", "id": ["15486"], "page_name": "Port master"}, {"page_name_sub": "Port master#Land's End", "id": ["15472"], "page_name": "Port master"}, {"page_name_sub": "Port master#Entrana", "id": ["15463"], "page_name": "Port master"}, {"page_name_sub": "Skylark", "id": ["9"], "page_name": "Skylark"}, {"page_name_sub": "Beaver (larch)", "id": ["beta14344"], "page_name": "Beaver (larch)"}, {"page_name_sub": "Shark (Sailing)", "id": ["beta15039"], "page_name": "Shark (Sailing)"}, {"page_name_sub": "Shark (Sailing)", "id": ["beta15040"], "page_name": "Shark (Sailing)"}, {"page_name_sub": "Parrot (Last Light)#Parrot", "id": ["15046"], "page_name": "Parrot (Last Light)"}, {"page_name_sub": "Parrot (Last Light)#Cage", "id": ["15048"], "page_name": "Parrot (Last Light)"}, {"page_name_sub": "Parrot (Last Light)#Free", "id": ["15047"], "page_name": "Parrot (Last Light)"}, {"page_name_sub": "Soldier (Lizardman kill count)", "id": ["6877"], "page_name": "Soldier (Lizardman kill count)"}, {"page_name_sub": "Jug (Tombs of Amascut)#Moving", "id": ["11736"], "page_name": "Jug (Tombs of Amascut)"}, {"page_name_sub": "Jug (Tombs of Amascut)#Stationary", "id": ["11735"], "page_name": "Jug (Tombs of Amascut)"}, {"page_name_sub": "Barrelchest (Nightmare Zone)#Hard Mode", "id": ["1126"], "page_name": "Barrelchest (Nightmare Zone)"}, {"page_name_sub": "Barrelchest (Nightmare Zone)#Normal Mode", "id": ["6342"], "page_name": "Barrelchest (Nightmare Zone)"}, {"page_name_sub": "Lightning cloud (Sailing)", "id": ["15490"], "page_name": "Lightning cloud (Sailing)"}, {"page_name_sub": "Goopy snake", "id": ["2990"], "page_name": "Goopy snake"}, {"page_name_sub": "Fire (Tempoross Cove)", "id": ["8643"], "page_name": "Fire (Tempoross Cove)"}, {"page_name_sub": "Armoured zombie (Defender of Varrock)#Melee (invasion)", "id": ["12730", "12731", "12732", "12733", "12734", "12736", "12738", "12755", "12757", "12758"], "page_name": "Armoured zombie (Defender of Varrock)"}, {"page_name_sub": "Armoured zombie (Defender of Varrock)#Ranged (invasion)", "id": ["12735", "12738", "12739", "12761", "12763", "12764"], "page_name": "Armoured zombie (Defender of Varrock)"}, {"page_name_sub": "Chair (Draynor Manor)", "id": ["3567"], "page_name": "Chair (Draynor Manor)"}, {"page_name_sub": "Seal (Sailing)", "id": ["beta14278"], "page_name": "Seal (Sailing)"}, {"page_name_sub": "Seal (Sailing)", "id": ["beta14279"], "page_name": "Seal (Sailing)"}, {"page_name_sub": "Siren (Sailing)", "id": ["beta15075"], "page_name": "Siren (Sailing)"}, {"page_name_sub": "Siren (Sailing)", "id": ["beta15076"], "page_name": "Siren (Sailing)"}, {"page_name_sub": "Bella Le Bowle", "id": ["hist14208"], "page_name": "Bella Le Bowle"}, {"page_name_sub": "Glanton#Normal", "id": ["hist14181", "hist14182", "hist14206"], "page_name": "Glanton"}, {"page_name_sub": "Glanton#Performance", "id": ["hist14181", "hist14182", "hist14206"], "page_name": "Glanton"}, {"page_name_sub": "Doughphie", "id": ["hist14203"], "page_name": "Doughphie"}, {"page_name_sub": "The mouth of Clarence", "id": ["hist14202"], "page_name": "The mouth of Clarence"}, {"page_name_sub": "Bowley Moley", "id": ["hist14188", "hist14191"], "page_name": "Bowley Moley"}, {"page_name_sub": "Fry", "id": ["hist14189", "hist14194"], "page_name": "Fry"}, {"page_name_sub": "Eggus Manus#Normal", "id": ["hist14187", "hist14193"], "page_name": "Eggus Manus"}, {"page_name_sub": "Eggus Manus#Performance", "id": ["hist14187", "hist14193"], "page_name": "Eggus Manus"}, {"page_name_sub": "Concerned man", "id": ["hist14179"], "page_name": "Concerned man"}, {"page_name_sub": "Wheeler", "id": ["hist14186"], "page_name": "Wheeler"}, {"page_name_sub": "Cooky Weasel", "id": ["hist14185"], "page_name": "Cooky Weasel"}, {"page_name_sub": "Rinder#Normal", "id": ["hist14183", "hist14184", "hist14207"], "page_name": "Rinder"}, {"page_name_sub": "Rinder#Performance", "id": ["hist14183", "hist14184", "hist14207"], "page_name": "Rinder"}, {"page_name_sub": "Clarence (2025 Easter event)", "id": ["hist14201"], "page_name": "Clarence (2025 Easter event)"}, {"page_name_sub": "Scorpion (2025 Easter event)", "id": ["hist14190"], "page_name": "Scorpion (2025 Easter event)"}, {"page_name_sub": "River troll (random event)#Level 79", "id": ["hist5887"], "page_name": "River troll (random event)"}, {"page_name_sub": "River troll (random event)#Level 159", "id": ["hist5889"], "page_name": "River troll (random event)"}, {"page_name_sub": "River troll (random event)#Level 29", "id": ["hist5885"], "page_name": "River troll (random event)"}, {"page_name_sub": "River troll (random event)#Level 14", "id": ["hist5884"], "page_name": "River troll (random event)"}, {"page_name_sub": "River troll (random event)#Level 120", "id": ["hist5888"], "page_name": "River troll (random event)"}, {"page_name_sub": "River troll (random event)#Level 49", "id": ["hist5886"], "page_name": "River troll (random event)"}, {"page_name_sub": "Butterfly (Draugen)", "id": ["3923"], "page_name": "Butterfly (Draugen)"}, {"page_name_sub": "Void Flare#Shadow", "id": ["14179"], "page_name": "Void Flare"}, {"page_name_sub": "Void Flare#Fire", "id": ["14179"], "page_name": "Void Flare"}, {"page_name_sub": "Yami", "id": ["14203", "14204"], "page_name": "Yami"}, {"page_name_sub": "Jim#Before meeting", "id": ["14200"], "page_name": "Jim"}, {"page_name_sub": "Jim#Wet cloth", "id": ["14199", "14202"], "page_name": "Jim"}, {"page_name_sub": "Jim#After meeting", "id": ["14201"], "page_name": "Jim"}, {"page_name_sub": "Soldier (Chasm of Fire)#Scimitar", "id": ["14191"], "page_name": "Soldier (Chasm of Fire)"}, {"page_name_sub": "Soldier (Chasm of Fire)#Warhammer", "id": ["14189"], "page_name": "Soldier (Chasm of Fire)"}, {"page_name_sub": "Soldier (Chasm of Fire)#Dagger", "id": ["14193"], "page_name": "Soldier (Chasm of Fire)"}, {"page_name_sub": "Sergeant (Chasm of Fire)", "id": ["14197"], "page_name": "Sergeant (Chasm of Fire)"}, {"page_name_sub": "Lieutenant (Chasm of Fire)", "id": ["14195"], "page_name": "Lieutenant (Chasm of Fire)"}, {"page_name_sub": "Judge of Yama", "id": ["14180"], "page_name": "Judge of Yama"}, {"page_name_sub": "Imp (Yama)", "id": ["14181"], "page_name": "Imp (Yama)"}, {"page_name_sub": "Agrith Naar (Nightmare Zone)#Hard Mode", "id": ["6327"], "page_name": "Agrith Naar (Nightmare Zone)"}, {"page_name_sub": "Agrith Naar (Nightmare Zone)#Normal Mode", "id": ["6388"], "page_name": "Agrith Naar (Nightmare Zone)"}, {"page_name_sub": "Agrith-Na-Na (Nightmare Zone)#Hard Mode", "id": ["6308"], "page_name": "Agrith-Na-Na (Nightmare Zone)"}, {"page_name_sub": "Agrith-Na-Na (Nightmare Zone)#Normal Mode", "id": ["6369"], "page_name": "Agrith-Na-Na (Nightmare Zone)"}, {"page_name_sub": "Arrg (Nightmare Zone)#Hard Mode", "id": ["6331"], "page_name": "Arrg (Nightmare Zone)"}, {"page_name_sub": "Arrg (Nightmare Zone)#Normal Mode", "id": ["6392"], "page_name": "Arrg (Nightmare Zone)"}, {"page_name_sub": "Black demon (Nightmare Zone)#Hard Mode", "id": ["6295"], "page_name": "Black demon (Nightmare Zone)"}, {"page_name_sub": "Black demon (Nightmare Zone)#Normal Mode", "id": ["6357"], "page_name": "Black demon (Nightmare Zone)"}, {"page_name_sub": "Black Knight Titan (Nightmare Zone)#Hard Mode", "id": ["6299"], "page_name": "Black Knight Titan (Nightmare Zone)"}, {"page_name_sub": "Black Knight Titan (Nightmare Zone)#Normal Mode", "id": ["6360"], "page_name": "Black Knight Titan (Nightmare Zone)"}, {"page_name_sub": "Bouncer (Nightmare Zone)#Hard Mode", "id": ["6293"], "page_name": "Bouncer (Nightmare Zone)"}, {"page_name_sub": "Bouncer (Nightmare Zone)#Normal Mode", "id": ["6355"], "page_name": "Bouncer (Nightmare Zone)"}, {"page_name_sub": "Elvarg (Nightmare Zone)#Hard Mode", "id": ["6118"], "page_name": "Elvarg (Nightmare Zone)"}, {"page_name_sub": "Elvarg (Nightmare Zone)#Normal Mode", "id": ["6349"], "page_name": "Elvarg (Nightmare Zone)"}, {"page_name_sub": "Chronozon (Nightmare Zone)#Hard Mode", "id": ["6292"], "page_name": "Chronozon (Nightmare Zone)"}, {"page_name_sub": "Chronozon (Nightmare Zone)#Normal Mode", "id": ["6354"], "page_name": "Chronozon (Nightmare Zone)"}, {"page_name_sub": "Skeleton Hellhound (Nightmare Zone)#Hard Mode", "id": ["6326"], "page_name": "Skeleton Hellhound (Nightmare Zone)"}, {"page_name_sub": "Skeleton Hellhound (Nightmare Zone)#Normal Mode", "id": ["6387"], "page_name": "Skeleton Hellhound (Nightmare Zone)"}, {"page_name_sub": "Nezikchened (Nightmare Zone)#Hard Mode", "id": ["6318"], "page_name": "Nezikchened (Nightmare Zone)"}, {"page_name_sub": "Nezikchened (Nightmare Zone)#Normal Mode", "id": ["6379"], "page_name": "Nezikchened (Nightmare Zone)"}, {"page_name_sub": "Jungle Demon (Nightmare Zone)#Hard Mode", "id": ["6321"], "page_name": "Jungle Demon (Nightmare Zone)"}, {"page_name_sub": "Jungle Demon (Nightmare Zone)#Normal Mode", "id": ["6382"], "page_name": "Jungle Demon (Nightmare Zone)"}, {"page_name_sub": "Arianwyn (Nightmare Zone)#Hard Mode", "id": ["9246"], "page_name": "Arianwyn (Nightmare Zone)"}, {"page_name_sub": "Arianwyn (Nightmare Zone)#Normal Mode", "id": ["9248"], "page_name": "Arianwyn (Nightmare Zone)"}, {"page_name_sub": "Essyllt (Nightmare Zone)#Hard Mode", "id": ["9247"], "page_name": "Essyllt (Nightmare Zone)"}, {"page_name_sub": "Essyllt (Nightmare Zone)#Normal Mode", "id": ["9249"], "page_name": "Essyllt (Nightmare Zone)"}, {"page_name_sub": "Corrupt Lizardman (Nightmare Zone)#Hard Mode", "id": ["7996"], "page_name": "Corrupt Lizardman (Nightmare Zone)"}, {"page_name_sub": "Corrupt Lizardman (Nightmare Zone)#Normal Mode", "id": ["7997"], "page_name": "Corrupt Lizardman (Nightmare Zone)"}, {"page_name_sub": "Culinaromancer (Nightmare Zone)#Hard Mode", "id": ["6307"], "page_name": "Culinaromancer (Nightmare Zone)"}, {"page_name_sub": "Culinaromancer (Nightmare Zone)#Normal Mode", "id": ["6368"], "page_name": "Culinaromancer (Nightmare Zone)"}, {"page_name_sub": "Dessourt (Nightmare Zone)#Hard Mode", "id": ["6311"], "page_name": "Dessourt (Nightmare Zone)"}, {"page_name_sub": "Dessourt (Nightmare Zone)#Normal Mode", "id": ["6372"], "page_name": "Dessourt (Nightmare Zone)"}, {"page_name_sub": "Flambeed (Nightmare Zone)#Hard Mode", "id": ["6309"], "page_name": "Flambeed (Nightmare Zone)"}, {"page_name_sub": "Flambeed (Nightmare Zone)#Normal Mode", "id": ["6370"], "page_name": "Flambeed (Nightmare Zone)"}, {"page_name_sub": "Gelatinnoth Mother (Nightmare Zone)#Hard Mode", "id": ["6312", "6313", "6314", "6315", "6316", "6317"], "page_name": "Gelatinnoth Mother (Nightmare Zone)"}, {"page_name_sub": "Gelatinnoth Mother (Nightmare Zone)#Normal Mode", "id": ["6373", "6374", "6375", "6376", "6377", "6378"], "page_name": "Gelatinnoth Mother (Nightmare Zone)"}, {"page_name_sub": "Karamel (Nightmare Zone)#Hard Mode", "id": ["6310"], "page_name": "Karamel (Nightmare Zone)"}, {"page_name_sub": "Karamel (Nightmare Zone)#Normal Mode", "id": ["6371"], "page_name": "Karamel (Nightmare Zone)"}, {"page_name_sub": "Dagannoth mother (Nightmare Zone)#Hard Mode", "id": ["6300", "6301", "6302", "6303", "6304", "6305"], "page_name": "Dagannoth mother (Nightmare Zone)"}, {"page_name_sub": "Dagannoth mother (Nightmare Zone)#Normal Mode", "id": ["6361", "6362", "6363", "6364", "6365", "6366"], "page_name": "Dagannoth mother (Nightmare Zone)"}, {"page_name_sub": "Dad (Nightmare Zone)#Hard Mode", "id": ["6330"], "page_name": "Dad (Nightmare Zone)"}, {"page_name_sub": "Dad (Nightmare Zone)#Normal Mode", "id": ["6391"], "page_name": "Dad (Nightmare Zone)"}, {"page_name_sub": "Damis (Nightmare Zone)#Second form (Normal Mode)", "id": ["6347"], "page_name": "Damis (Nightmare Zone)"}, {"page_name_sub": "Damis (Nightmare Zone)#First form (Normal Mode)", "id": ["6346"], "page_name": "Damis (Nightmare Zone)"}, {"page_name_sub": "Damis (Nightmare Zone)#First form (Hard Mode)", "id": ["1134"], "page_name": "Damis (Nightmare Zone)"}, {"page_name_sub": "Damis (Nightmare Zone)#Second form (Hard Mode)", "id": ["1135"], "page_name": "Damis (Nightmare Zone)"}, {"page_name_sub": "Dessous (Nightmare Zone)#Hard Mode", "id": ["1128"], "page_name": "Dessous (Nightmare Zone)"}, {"page_name_sub": "Dessous (Nightmare Zone)#Normal Mode", "id": ["6344"], "page_name": "Dessous (Nightmare Zone)"}, {"page_name_sub": "Spooky chair", "id": ["14815"], "page_name": "Spooky chair"}, {"page_name_sub": "Me (Nightmare Zone)#Hard Mode", "id": ["6320"], "page_name": "Me (Nightmare Zone)"}, {"page_name_sub": "Me (Nightmare Zone)#Normal Mode", "id": ["6381"], "page_name": "Me (Nightmare Zone)"}, {"page_name_sub": "Treus Dayth (Nightmare Zone)#Hard Mode", "id": ["6298"], "page_name": "Treus Dayth (Nightmare Zone)"}, {"page_name_sub": "Treus Dayth (Nightmare Zone)#Normal Mode", "id": ["6359"], "page_name": "Treus Dayth (Nightmare Zone)"}, {"page_name_sub": "Witch's experiment (Nightmare Zone)#Skavid (Hard Mode)", "id": ["6333"], "page_name": "Witch's experiment (Nightmare Zone)"}, {"page_name_sub": "Witch's experiment (Nightmare Zone)#Wolf (Hard Mode)", "id": ["6336"], "page_name": "Witch's experiment (Nightmare Zone)"}, {"page_name_sub": "Witch's experiment (Nightmare Zone)#Bear (Hard Mode)", "id": ["6335"], "page_name": "Witch's experiment (Nightmare Zone)"}, {"page_name_sub": "Witch's experiment (Nightmare Zone)#Spider (Hard Mode)", "id": ["6334"], "page_name": "Witch's experiment (Nightmare Zone)"}, {"page_name_sub": "Witch's experiment (Nightmare Zone)#Skavid (Normal Mode)", "id": ["6394"], "page_name": "Witch's experiment (Nightmare Zone)"}, {"page_name_sub": "Witch's experiment (Nightmare Zone)#Spider (Normal Mode)", "id": ["6395"], "page_name": "Witch's experiment (Nightmare Zone)"}, {"page_name_sub": "Witch's experiment (Nightmare Zone)#Wolf (Normal Mode)", "id": ["6397"], "page_name": "Witch's experiment (Nightmare Zone)"}, {"page_name_sub": "Witch's experiment (Nightmare Zone)#Bear (Normal Mode)", "id": ["6396"], "page_name": "Witch's experiment (Nightmare Zone)"}, {"page_name_sub": "King Roald (Nightmare Zone)#Hard Mode", "id": ["6328"], "page_name": "King Roald (Nightmare Zone)"}, {"page_name_sub": "King Roald (Nightmare Zone)#Normal Mode", "id": ["6389"], "page_name": "King Roald (Nightmare Zone)"}, {"page_name_sub": "Tree spirit (Nightmare Zone)#Hard Mode", "id": ["6319"], "page_name": "Tree spirit (Nightmare Zone)"}, {"page_name_sub": "Tree spirit (Nightmare Zone)#Normal Mode", "id": ["6380"], "page_name": "Tree spirit (Nightmare Zone)"}, {"page_name_sub": "Slagilith (Nightmare Zone)#Hard Mode", "id": ["6324"], "page_name": "Slagilith (Nightmare Zone)"}, {"page_name_sub": "Slagilith (Nightmare Zone)#Normal Mode", "id": ["6385"], "page_name": "Slagilith (Nightmare Zone)"}, {"page_name_sub": "Nazastarool (Nightmare Zone)#Zombie (Hard Mode)", "id": ["6337"], "page_name": "Nazastarool (Nightmare Zone)"}, {"page_name_sub": "Nazastarool (Nightmare Zone)#Skeleton (Hard Mode)", "id": ["6338"], "page_name": "Nazastarool (Nightmare Zone)"}, {"page_name_sub": "Nazastarool (Nightmare Zone)#Skeleton (Normal Mode)", "id": ["6399"], "page_name": "Nazastarool (Nightmare Zone)"}, {"page_name_sub": "Nazastarool (Nightmare Zone)#Ghost (Hard Mode)", "id": ["6339"], "page_name": "Nazastarool (Nightmare Zone)"}, {"page_name_sub": "Nazastarool (Nightmare Zone)#Ghost (Normal Mode)", "id": ["6400"], "page_name": "Nazastarool (Nightmare Zone)"}, {"page_name_sub": "Nazastarool (Nightmare Zone)#Zombie (Normal Mode)", "id": ["6398"], "page_name": "Nazastarool (Nightmare Zone)"}, {"page_name_sub": "The Everlasting (Nightmare Zone)#Hard Mode", "id": ["6120"], "page_name": "The Everlasting (Nightmare Zone)"}, {"page_name_sub": "The Everlasting (Nightmare Zone)#Normal Mode", "id": ["6351"], "page_name": "The Everlasting (Nightmare Zone)"}, {"page_name_sub": "The Inadequacy (Nightmare Zone)#Hard Mode", "id": ["6119"], "page_name": "The Inadequacy (Nightmare Zone)"}, {"page_name_sub": "The Inadequacy (Nightmare Zone)#Normal Mode", "id": ["6350"], "page_name": "The Inadequacy (Nightmare Zone)"}, {"page_name_sub": "The Untouchable (Nightmare Zone)#Hard Mode", "id": ["6121"], "page_name": "The Untouchable (Nightmare Zone)"}, {"page_name_sub": "The Untouchable (Nightmare Zone)#Normal Mode", "id": ["6352"], "page_name": "The Untouchable (Nightmare Zone)"}, {"page_name_sub": "Fareed (Nightmare Zone)#Hard Mode", "id": ["4115"], "page_name": "Fareed (Nightmare Zone)"}, {"page_name_sub": "Fareed (Nightmare Zone)#Normal Mode", "id": ["6348"], "page_name": "Fareed (Nightmare Zone)"}, {"page_name_sub": "Kamil (Nightmare Zone)#Hard Mode", "id": ["1129"], "page_name": "Kamil (Nightmare Zone)"}, {"page_name_sub": "Kamil (Nightmare Zone)#Normal Mode", "id": ["6345"], "page_name": "Kamil (Nightmare Zone)"}, {"page_name_sub": "Khazard warlord (Nightmare Zone)#Hard Mode", "id": ["6329"], "page_name": "Khazard warlord (Nightmare Zone)"}, {"page_name_sub": "Khazard warlord (Nightmare Zone)#Normal Mode", "id": ["6390"], "page_name": "Khazard warlord (Nightmare Zone)"}, {"page_name_sub": "The Kendal (Nightmare Zone)#Hard Mode", "id": ["6322"], "page_name": "The Kendal (Nightmare Zone)"}, {"page_name_sub": "The Kendal (Nightmare Zone)#Normal Mode", "id": ["6383"], "page_name": "The Kendal (Nightmare Zone)"}, {"page_name_sub": "Sand Snake (Nightmare Zone)#Normal", "id": ["7895"], "page_name": "Sand Snake (Nightmare Zone)"}, {"page_name_sub": "Sand Snake (Nightmare Zone)#Hard", "id": ["7894"], "page_name": "Sand Snake (Nightmare Zone)"}, {"page_name_sub": "Trapped Soul (Nightmare Zone)#Hard Mode", "id": ["8529"], "page_name": "Trapped Soul (Nightmare Zone)"}, {"page_name_sub": "Trapped Soul (Nightmare Zone)#Normal Mode", "id": ["8528"], "page_name": "Trapped Soul (Nightmare Zone)"}, {"page_name_sub": "Tanglefoot (Nightmare Zone)#Hard Mode", "id": ["6291"], "page_name": "Tanglefoot (Nightmare Zone)"}, {"page_name_sub": "Tanglefoot (Nightmare Zone)#Normal Mode", "id": ["6353"], "page_name": "Tanglefoot (Nightmare Zone)"}, {"page_name_sub": "Headless Beast (Nightmare Zone)#Hard Mode", "id": ["10492"], "page_name": "Headless Beast (Nightmare Zone)"}, {"page_name_sub": "Headless Beast (Nightmare Zone)#Normal Mode", "id": ["10493"], "page_name": "Headless Beast (Nightmare Zone)"}, {"page_name_sub": "Glod (Nightmare Zone)#Hard Mode", "id": ["6297"], "page_name": "Glod (Nightmare Zone)"}, {"page_name_sub": "Glod (Nightmare Zone)#Normal Mode", "id": ["6358"], "page_name": "Glod (Nightmare Zone)"}, {"page_name_sub": "Giant Scarab (Nightmare Zone)#Hard Mode", "id": ["1127"], "page_name": "Giant Scarab (Nightmare Zone)"}, {"page_name_sub": "Giant Scarab (Nightmare Zone)#Normal Mode", "id": ["6343"], "page_name": "Giant Scarab (Nightmare Zone)"}, {"page_name_sub": "Giant Roc (Nightmare Zone)#Hard Mode", "id": ["6323"], "page_name": "Giant Roc (Nightmare Zone)"}, {"page_name_sub": "Giant Roc (Nightmare Zone)#Normal Mode", "id": ["6384"], "page_name": "Giant Roc (Nightmare Zone)"}, {"page_name_sub": "Mayor of catherby", "id": ["15050"], "page_name": "Mayor of catherby"}, {"page_name_sub": "Floopa#Injured, unnamed", "id": ["14990"], "page_name": "Floopa"}, {"page_name_sub": "Floopa#Troubled Tortugans, recovering 1", "id": ["14992"], "page_name": "Floopa"}, {"page_name_sub": "Floopa#The Red Reef", "id": ["15012"], "page_name": "Floopa"}, {"page_name_sub": "Floopa#Recovering, unnamed", "id": ["14991"], "page_name": "Floopa"}, {"page_name_sub": "Floopa#Troubled Tortugans", "id": ["14994"], "page_name": "Floopa"}, {"page_name_sub": "Floopa#Troubled Tortugans, recovering 2", "id": ["14993"], "page_name": "Floopa"}, {"page_name_sub": "Receptionist", "id": ["15013"], "page_name": "Receptionist"}, {"page_name_sub": "Theodore Paxton", "id": ["15015"], "page_name": "Theodore Paxton"}, {"page_name_sub": "Spencer Brentwood#Normal", "id": ["15017"], "page_name": "Spencer Brentwood"}, {"page_name_sub": "Spencer Brentwood#Diving", "id": ["15020"], "page_name": "Spencer Brentwood"}, {"page_name_sub": "Black Eye Bethel", "id": ["15025"], "page_name": "Black Eye Bethel"}, {"page_name_sub": "Chief Engineer Greyson", "id": ["15035"], "page_name": "Chief Engineer Greyson"}, {"page_name_sub": "Captain Maclean", "id": ["15036"], "page_name": "Captain Maclean"}, {"page_name_sub": "Councillor Catherine", "id": ["14952"], "page_name": "Councillor Catherine"}, {"page_name_sub": "Elder Hubber", "id": ["15003", "15004", "15005"], "page_name": "Elder Hubber"}, {"page_name_sub": "Elder Root", "id": ["15006", "15007", "15008"], "page_name": "Elder Root"}, {"page_name_sub": "Elder Coco", "id": ["14828", "14829"], "page_name": "Elder Coco"}, {"page_name_sub": "Elder Strom", "id": ["14831", "14832"], "page_name": "Elder Strom"}, {"page_name_sub": "Elder Krill", "id": ["14834", "14835"], "page_name": "Elder Krill"}, {"page_name_sub": "Elder Blunn", "id": ["14837", "14838"], "page_name": "Elder Blunn"}, {"page_name_sub": "Elder Reggle", "id": ["14843", "14844"], "page_name": "Elder Reggle"}, {"page_name_sub": "Elder Katt", "id": ["14846"], "page_name": "Elder Katt"}, {"page_name_sub": "Leff", "id": ["14848"], "page_name": "Leff"}, {"page_name_sub": "Dalna", "id": ["14849"], "page_name": "Dalna"}, {"page_name_sub": "Amma", "id": ["14851"], "page_name": "Amma"}, {"page_name_sub": "Elder Kelmo", "id": ["14861"], "page_name": "Elder Kelmo"}, {"page_name_sub": "Elder Nama", "id": ["14863"], "page_name": "Elder Nama"}, {"page_name_sub": "Mako", "id": ["14816"], "page_name": "Mako"}, {"page_name_sub": "Blenny", "id": ["14818"], "page_name": "Blenny"}, {"page_name_sub": "Cabin Boy Percy", "id": ["14819"], "page_name": "Cabin Boy Percy"}, {"page_name_sub": "Griems", "id": ["14821"], "page_name": "Griems"}, {"page_name_sub": "Cochu", "id": ["14822"], "page_name": "Cochu"}, {"page_name_sub": "Ling", "id": ["14823"], "page_name": "Ling"}, {"page_name_sub": "Belle", "id": ["14825"], "page_name": "Belle"}, {"page_name_sub": "Ide", "id": ["14826"], "page_name": "Ide"}, {"page_name_sub": "Chet#During Troubled Tortugans", "id": ["15063"], "page_name": "Chet"}, {"page_name_sub": "Chet#After Troubled Tortugans", "id": ["15062"], "page_name": "Chet"}, {"page_name_sub": "Guppa", "id": ["15064"], "page_name": "Guppa"}, {"page_name_sub": "Port Wizard Paulie", "id": ["15381"], "page_name": "Port Wizard Paulie"}, {"page_name_sub": "Captain Jim", "id": ["beta14444"], "page_name": "Captain Jim"}, {"page_name_sub": "Captain Ada", "id": ["beta14445"], "page_name": "Captain Ada"}, {"page_name_sub": "Mr Face", "id": ["beta14446"], "page_name": "Mr Face"}, {"page_name_sub": "Hammerhead shark", "id": ["15196"], "page_name": "Hammerhead shark"}, {"page_name_sub": "Hammerhead shark", "id": ["15197"], "page_name": "Hammerhead shark"}, {"page_name_sub": "Wuss", "id": ["beta14503"], "page_name": "Wuss"}, {"page_name_sub": "Gurtob", "id": ["15099", "15100", "15101"], "page_name": "Gurtob"}, {"page_name_sub": "Gwyna", "id": ["15106", "15107", "15108"], "page_name": "Gwyna"}, {"page_name_sub": "Ocean Man", "id": ["15116"], "page_name": "Ocean Man"}, {"page_name_sub": "Giant clam#Pearl", "id": ["15122"], "page_name": "Giant clam"}, {"page_name_sub": "Giant clam#Open", "id": ["15120"], "page_name": "Giant clam"}, {"page_name_sub": "Giant clam#Closed", "id": ["15121"], "page_name": "Giant clam"}, {"page_name_sub": "Clue turtle", "id": ["15124"], "page_name": "Clue turtle"}, {"page_name_sub": "Adventurer Ada#Cargo 2", "id": ["15268"], "page_name": "Adventurer Ada"}, {"page_name_sub": "Adventurer Ada#Cargo 3", "id": ["15269"], "page_name": "Adventurer Ada"}, {"page_name_sub": "Adventurer Ada#Dock", "id": ["15263"], "page_name": "Adventurer Ada"}, {"page_name_sub": "Adventurer Ada#Command", "id": ["15265"], "page_name": "Adventurer Ada"}, {"page_name_sub": "Adventurer Ada#Talk-to", "id": ["15262"], "page_name": "Adventurer Ada"}, {"page_name_sub": "Adventurer Ada#Cargo 1", "id": ["15267"], "page_name": "Adventurer Ada"}, {"page_name_sub": "Adventurer Ada#No-op", "id": ["15266"], "page_name": "Adventurer Ada"}, {"page_name_sub": "Jittery Jim#Cargo 2", "id": ["15278"], "page_name": "Jittery Jim"}, {"page_name_sub": "Jittery Jim#Cargo 3", "id": ["15279"], "page_name": "Jittery Jim"}, {"page_name_sub": "Jittery Jim#Dock", "id": ["15273"], "page_name": "Jittery Jim"}, {"page_name_sub": "Jittery Jim#Command", "id": ["15275"], "page_name": "Jittery Jim"}, {"page_name_sub": "Jittery Jim#Talk-to", "id": ["15272"], "page_name": "Jittery Jim"}, {"page_name_sub": "Jittery Jim#Cargo 1", "id": ["15277"], "page_name": "Jittery Jim"}, {"page_name_sub": "Jittery Jim#No-op", "id": ["15276"], "page_name": "Jittery Jim"}, {"page_name_sub": "Jolly Jim#Cargo 2", "id": ["15288"], "page_name": "Jolly Jim"}, {"page_name_sub": "Jolly Jim#Cargo 3", "id": ["15289"], "page_name": "Jolly Jim"}, {"page_name_sub": "Jolly Jim#Dock", "id": ["15283"], "page_name": "Jolly Jim"}, {"page_name_sub": "Jolly Jim#Command", "id": ["15285"], "page_name": "Jolly Jim"}, {"page_name_sub": "Jolly Jim#Talk-to", "id": ["15282"], "page_name": "Jolly Jim"}, {"page_name_sub": "Jolly Jim#Cargo 1", "id": ["15287"], "page_name": "Jolly Jim"}, {"page_name_sub": "Jolly Jim#No-op", "id": ["15286"], "page_name": "Jolly Jim"}, {"page_name_sub": "Sailor Jakob#Cargo 2", "id": ["15298"], "page_name": "Sailor Jakob"}, {"page_name_sub": "Sailor Jakob#Cargo 3", "id": ["15299"], "page_name": "Sailor Jakob"}, {"page_name_sub": "Sailor Jakob#Dock", "id": ["15293"], "page_name": "Sailor Jakob"}, {"page_name_sub": "Sailor Jakob#Command", "id": ["15295"], "page_name": "Sailor Jakob"}, {"page_name_sub": "Sailor Jakob#Talk-to", "id": ["15292"], "page_name": "Sailor Jakob"}, {"page_name_sub": "Sailor Jakob#Cargo 1", "id": ["15297"], "page_name": "Sailor Jakob"}, {"page_name_sub": "Sailor Jakob#No-op", "id": ["15296"], "page_name": "Sailor Jakob"}, {"page_name_sub": "Oarswoman Olga#Cargo 2", "id": ["15308"], "page_name": "Oarswoman Olga"}, {"page_name_sub": "Oarswoman Olga#Cargo 3", "id": ["15309"], "page_name": "Oarswoman Olga"}, {"page_name_sub": "Oarswoman Olga#Dock", "id": ["15303"], "page_name": "Oarswoman Olga"}, {"page_name_sub": "Oarswoman Olga#Command", "id": ["15305"], "page_name": "Oarswoman Olga"}, {"page_name_sub": "Oarswoman Olga#Talk-to", "id": ["15302"], "page_name": "Oarswoman Olga"}, {"page_name_sub": "Oarswoman Olga#Cargo 1", "id": ["15307"], "page_name": "Oarswoman Olga"}, {"page_name_sub": "Oarswoman Olga#No-op", "id": ["15306"], "page_name": "Oarswoman Olga"}, {"page_name_sub": "Bosun Zarah#Cargo 2", "id": ["15318"], "page_name": "Bosun Zarah"}, {"page_name_sub": "Bosun Zarah#Cargo 3", "id": ["15319"], "page_name": "Bosun Zarah"}, {"page_name_sub": "Bosun Zarah#Dock", "id": ["15313"], "page_name": "Bosun Zarah"}, {"page_name_sub": "Bosun Zarah#Command", "id": ["15315"], "page_name": "Bosun Zarah"}, {"page_name_sub": "Bosun Zarah#Talk-to", "id": ["15312"], "page_name": "Bosun Zarah"}, {"page_name_sub": "Bosun Zarah#Cargo 1", "id": ["15317"], "page_name": "Bosun Zarah"}, {"page_name_sub": "Bosun Zarah#No-op", "id": ["15316"], "page_name": "Bosun Zarah"}, {"page_name_sub": "Spotter Virginia#Cargo 2", "id": ["15328"], "page_name": "Spotter Virginia"}, {"page_name_sub": "Spotter Virginia#Docks", "id": ["15323"], "page_name": "Spotter Virginia"}, {"page_name_sub": "Spotter Virginia#Cargo 3", "id": ["15329"], "page_name": "Spotter Virginia"}, {"page_name_sub": "Spotter Virginia#Command", "id": ["15325"], "page_name": "Spotter Virginia"}, {"page_name_sub": "Spotter Virginia#Talk-to", "id": ["15322"], "page_name": "Spotter Virginia"}, {"page_name_sub": "Spotter Virginia#Cargo 1", "id": ["15327"], "page_name": "Spotter Virginia"}, {"page_name_sub": "Spotter Virginia#No-op", "id": ["15326"], "page_name": "Spotter Virginia"}]}