{"bucketQuery": "bucket('npc_id').select('page_name','page_name_sub','id').limit(500).offset(6500).run()", "bucket": [{"page_name_sub": "Avatar of Destruction", "id": ["10521"], "page_name": "Avatar of Destruction"}, {"page_name_sub": "Scrubfoot#Scrubfoot's cave", "id": ["10559"], "page_name": "Scrubfoot"}, {"page_name_sub": "Scrubfoot#2020 Christmas event", "id": ["hist10558"], "page_name": "Scrubfoot"}, {"page_name_sub": "Green fireflies#Decorative", "id": ["10564"], "page_name": "Green fireflies"}, {"page_name_sub": "Green fireflies#Catchable", "id": ["hist10565"], "page_name": "Green fireflies"}, {"page_name_sub": "Red fireflies#Decorative", "id": ["10561"], "page_name": "Red fireflies"}, {"page_name_sub": "Red fireflies#Catchable", "id": ["hist10562"], "page_name": "Red fireflies"}, {"page_name_sub": "Monk (Entrana)", "id": ["1171"], "page_name": "Monk (Entrana)"}, {"page_name_sub": "Tempoross#Enraged", "id": ["10575"], "page_name": "Tempoross"}, {"page_name_sub": "Tempoross#Surfaced", "id": ["10572"], "page_name": "Tempoross"}, {"page_name_sub": "Tempoross#Submerged", "id": ["10574"], "page_name": "Tempoross"}, {"page_name_sub": "Slave (daeyalt essence mine)#Bald", "id": ["9677"], "page_name": "Slave (daeyalt essence mine)"}, {"page_name_sub": "Slave (daeyalt essence mine)#Blue shirt", "id": ["9679"], "page_name": "Slave (daeyalt essence mine)"}, {"page_name_sub": "Slave (daeyalt essence mine)#Injured", "id": ["9682"], "page_name": "Slave (daeyalt essence mine)"}, {"page_name_sub": "Slave (daeyalt essence mine)#Green shirt", "id": ["9680"], "page_name": "Slave (daeyalt essence mine)"}, {"page_name_sub": "Slave (daeyalt essence mine)#Brown shirt", "id": ["9678"], "page_name": "Slave (daeyalt essence mine)"}, {"page_name_sub": "Slave (daeyalt essence mine)#Old", "id": ["9681"], "page_name": "Slave (daeyalt essence mine)"}, {"page_name_sub": "Gardener (unused)", "id": ["hist2668"], "page_name": "Gardener (unused)"}, {"page_name_sub": "Witch (monster)#Draynor Manor updated", "id": ["hist3566"], "page_name": "Witch (monster)"}, {"page_name_sub": "Witch (monster)#Al Kharid", "id": ["515"], "page_name": "Witch (monster)"}, {"page_name_sub": "Witch (monster)#Draynor Manor", "id": ["514"], "page_name": "Witch (monster)"}, {"page_name_sub": "Barman (unused)", "id": ["3304"], "page_name": "Barman (unused)"}, {"page_name_sub": "Farmer (Miscellania)", "id": ["3672"], "page_name": "Farmer (Miscellania)"}, {"page_name_sub": "Yrsa (Miscellania)", "id": ["3679"], "page_name": "Yrsa (Miscellania)"}, {"page_name_sub": "Ghost farmer", "id": ["3002"], "page_name": "Ghost farmer"}, {"page_name_sub": "Forgotten Soul#1", "id": ["10544"], "page_name": "Forgotten Soul"}, {"page_name_sub": "Forgotten Soul#2", "id": ["10545"], "page_name": "Forgotten Soul"}, {"page_name_sub": "Lil' creator#Lil' Creator", "id": ["2833", "3566"], "page_name": "Lil' creator"}, {"page_name_sub": "Lil' creator#Lil' Destructor", "id": ["3564", "5008"], "page_name": "Lil' creator"}, {"page_name_sub": "Chuck (Realm of Memories)", "id": ["hist10565", "hist15592"], "page_name": "Chuck (Realm of Memories)"}, {"page_name_sub": "Thrander", "id": ["hist10563", "hist15591"], "page_name": "Thrander"}, {"page_name_sub": "Troll (Realm of Memories)", "id": ["hist10588", "hist15613"], "page_name": "Troll (Realm of Memories)"}, {"page_name_sub": "Lizard man (Realm of Memories)", "id": ["hist10587", "hist15612"], "page_name": "Lizard man (Realm of Memories)"}, {"page_name_sub": "King black dragon (Realm of Memories)", "id": ["hist10579", "hist15604"], "page_name": "King black dragon (Realm of Memories)"}, {"page_name_sub": "Black dragon (Realm of Memories)", "id": ["hist10576", "hist15601"], "page_name": "Black dragon (Realm of Memories)"}, {"page_name_sub": "Blue dragon (Realm of Memories)", "id": ["hist10578", "hist15603"], "page_name": "Blue dragon (Realm of Memories)"}, {"page_name_sub": "Red dragon (Realm of Memories)", "id": ["hist10577", "hist15602"], "page_name": "Red dragon (Realm of Memories)"}, {"page_name_sub": "Baby blue dragon (Realm of Memories)", "id": ["hist10580", "hist15605"], "page_name": "Baby blue dragon (Realm of Memories)"}, {"page_name_sub": "Lesser demon (Realm of Memories)", "id": ["hist10581", "hist15606"], "page_name": "Lesser demon (Realm of Memories)"}, {"page_name_sub": "Greater demon (Realm of Memories)", "id": ["hist10582", "hist15607"], "page_name": "Greater demon (Realm of Memories)"}, {"page_name_sub": "Black demon (Realm of Memories)", "id": ["hist10583", "hist15608"], "page_name": "Black demon (Realm of Memories)"}, {"page_name_sub": "Scorpion (Realm of Memories)", "id": ["hist10584", "hist15609"], "page_name": "Scorpion (Realm of Memories)"}, {"page_name_sub": "King Scorpion (Realm of Memories)", "id": ["hist10585", "hist15610"], "page_name": "King Scorpion (Realm of Memories)"}, {"page_name_sub": "Orc (Realm of Memories)", "id": ["hist10586", "hist15611"], "page_name": "Orc (Realm of Memories)"}, {"page_name_sub": "Wolf (Soul Wars)", "id": ["10522", "10533"], "page_name": "Wolf (Soul Wars)"}, {"page_name_sub": "Cheerleader (Realm of Memories)#Spring green", "id": ["hist10574", "15600"], "page_name": "Cheerleader (Realm of Memories)"}, {"page_name_sub": "Cheerleader (Realm of Memories)#Blue", "id": ["hist10573", "15598"], "page_name": "Cheerleader (Realm of Memories)"}, {"page_name_sub": "Cheerleader (Realm of Memories)#Red", "id": ["hist10575", "15599"], "page_name": "Cheerleader (Realm of Memories)"}, {"page_name_sub": "Mysterious Watcher#Saradomin", "id": ["hist10569", "15594"], "page_name": "Mysterious Watcher"}, {"page_name_sub": "Mysterious Watcher#Zamorak", "id": ["hist10571", "15596"], "page_name": "Mysterious Watcher"}, {"page_name_sub": "Mysterious Watcher#Guthix", "id": ["hist10570", "15595"], "page_name": "Mysterious Watcher"}, {"page_name_sub": "Pious Pete (Realm of Memories)", "id": ["hist10568", "hist15593"], "page_name": "Pious Pete (Realm of Memories)"}, {"page_name_sub": "Imp (unused)", "id": ["removed"], "page_name": "Imp (unused)"}, {"page_name_sub": "Feral Vampyre (NPC)", "id": ["8678"], "page_name": "Feral Vampyre (NPC)"}, {"page_name_sub": "Duck (Soul Wars)#1", "id": ["10546"], "page_name": "Duck (Soul Wars)"}, {"page_name_sub": "Duck (Soul Wars)#2", "id": ["10547"], "page_name": "Duck (Soul Wars)"}, {"page_name_sub": "Guard (unused)", "id": ["removed"], "page_name": "Guard (unused)"}, {"page_name_sub": "Watchman (random event)#Random event", "id": ["removed"], "page_name": "Watchman (random event)"}, {"page_name_sub": "Watchman (random event)#Draynor Bank Robbery", "id": ["removed"], "page_name": "Watchman (random event)"}, {"page_name_sub": "Man (Canifis)#Green", "id": ["removed"], "page_name": "Man (Canifis)"}, {"page_name_sub": "Man (Canifis)#Blue", "id": ["removed"], "page_name": "Man (Canifis)"}, {"page_name_sub": "Man (Canifis)#Red", "id": ["removed"], "page_name": "Man (Canifis)"}, {"page_name_sub": "Woman (Canifis)#Yellow", "id": ["removed"], "page_name": "Woman (Canifis)"}, {"page_name_sub": "Woman (Canifis)#Red", "id": ["removed"], "page_name": "Woman (Canifis)"}, {"page_name_sub": "Woman (Canifis)#Purple", "id": ["removed"], "page_name": "Woman (Canifis)"}, {"page_name_sub": "Tramp (pillory)#Varrock", "id": ["381"], "page_name": "Tramp (pillory)"}, {"page_name_sub": "Tramp (pillory)#Yanille", "id": ["383"], "page_name": "Tramp (pillory)"}, {"page_name_sub": "Tramp (pillory)#Seers' Village", "id": ["382"], "page_name": "Tramp (pillory)"}, {"page_name_sub": "Goblin (Scrubfoot's cave)#Red", "id": ["10567"], "page_name": "Goblin (Scrubfoot's cave)"}, {"page_name_sub": "Goblin (Scrubfoot's cave)#Green", "id": ["10566"], "page_name": "Goblin (Scrubfoot's cave)"}, {"page_name_sub": "Urium Shade#Shade", "id": ["10589"], "page_name": "Urium Shade"}, {"page_name_sub": "Urium Shade#Shadow", "id": ["6143"], "page_name": "Urium Shade"}, {"page_name_sub": "Dampe", "id": ["10590"], "page_name": "Dampe"}, {"page_name_sub": "Undead Zealot#1", "id": ["10591"], "page_name": "Undead Zealot"}, {"page_name_sub": "Undead Zealot#2", "id": ["10592"], "page_name": "Undead Zealot"}, {"page_name_sub": "Garl", "id": ["10560"], "page_name": "Garl"}, {"page_name_sub": "Forgotten Soul (Soul Wars)#Level 76", "id": ["10525", "10526", "10536", "10537"], "page_name": "Forgotten Soul (Soul Wars)"}, {"page_name_sub": "Forgotten Soul (Soul Wars)#Level 46", "id": ["10523", "10524", "10534", "10535"], "page_name": "Forgotten Soul (Soul Wars)"}, {"page_name_sub": "Ancient Ghost#Aviansie", "id": ["10557"], "page_name": "Ancient Ghost"}, {"page_name_sub": "Ancient Ghost#Ork", "id": ["10558"], "page_name": "Ancient Ghost"}, {"page_name_sub": "Unicorn1337Kilr", "id": ["hist10609"], "page_name": "Unicorn1337Kilr"}, {"page_name_sub": "Sheep (2021 Birthday event)#Monkey on sheep", "id": ["hist10616", "hist10578", "10594", "hist10595", "hist10596"], "page_name": "Sheep (2021 Birthday event)"}, {"page_name_sub": "Sheep (2021 Birthday event)#Sheep", "id": ["hist10597"], "page_name": "Sheep (2021 Birthday event)"}, {"page_name_sub": "Monkey on cow#Cow", "id": ["hist10601"], "page_name": "Monkey on cow"}, {"page_name_sub": "Monkey on cow#Monkey on cow (1)", "id": ["hist10617", "10598"], "page_name": "Monkey on cow"}, {"page_name_sub": "Monkey on cow#Monkey on cow (2)", "id": ["hist10577", "hist10599", "hist10600"], "page_name": "Monkey on cow"}, {"page_name_sub": "Monkey on unicorn#Monkey on unicorn", "id": ["hist10618", "hist10579", "10603", "hist10604", "hist10605"], "page_name": "Monkey on unicorn"}, {"page_name_sub": "Monkey on unicorn#Unicorn", "id": ["hist10607"], "page_name": "Monkey on unicorn"}, {"page_name_sub": "Monkey on unicorn#Unicorn (level-15)", "id": ["hist10608"], "page_name": "Monkey on unicorn"}, {"page_name_sub": "Bob (2021 Birthday event)#Bob (with monkey)", "id": ["hist10574", "hist10610", "hist10580", "hist10581"], "page_name": "Bob (2021 Birthday event)"}, {"page_name_sub": "Bob (2021 Birthday event)#Bob", "id": ["hist10582", "hist10611"], "page_name": "Bob (2021 Birthday event)"}, {"page_name_sub": "Donie (2021 Birthday event)#Donie", "id": ["hist10562", "hist10585", "hist10586"], "page_name": "Donie (2021 Birthday event)"}, {"page_name_sub": "Donie (2021 Birthday event)#Donie (with monkey)", "id": ["hist10576", "hist10563", "hist10583", "hist10584"], "page_name": "Donie (2021 Birthday event)"}, {"page_name_sub": "Father Aereck (2021 Birthday event)#Father Aereck (with monkey)", "id": ["hist10575", "hist10565", "hist10587", "hist10588"], "page_name": "Father Aereck (2021 Birthday event)"}, {"page_name_sub": "Father Aereck (2021 Birthday event)#Father Aereck", "id": ["hist10593", "hist10568"], "page_name": "Father Aereck (2021 Birthday event)"}, {"page_name_sub": "Duke Horacio (2021 Birthday event)", "id": ["hist6817", "hist10569"], "page_name": "Duke Horacio (2021 Birthday event)"}, {"page_name_sub": "Mofina (2021 Birthday event)", "id": ["hist10615", "hist10573"], "page_name": "Mofina (2021 Birthday event)"}, {"page_name_sub": "Eluned (2021 Birthday event)", "id": ["hist10614", "hist10572"], "page_name": "Eluned (2021 Birthday event)"}, {"page_name_sub": "Awowogei (2021 Birthday event)", "id": ["hist10612", "hist10570"], "page_name": "Awowogei (2021 Birthday event)"}, {"page_name_sub": "Zeke (2021 Birthday event)", "id": ["hist10613", "hist10571"], "page_name": "Zeke (2021 Birthday event)"}, {"page_name_sub": "Cow (Nightmare Zone)#Hard Mode", "id": ["6340"], "page_name": "Cow (Nightmare Zone)"}, {"page_name_sub": "Cow (Nightmare Zone)#Normal Mode", "id": ["6401"], "page_name": "Cow (Nightmare Zone)"}, {"page_name_sub": "Woman (historical)", "id": ["3268"], "page_name": "Woman (historical)"}, {"page_name_sub": "White Knight (Burthorpe)", "id": ["4114"], "page_name": "White Knight (Burthorpe)"}, {"page_name_sub": "Karamthulhu (unused NPC)", "id": ["636"], "page_name": "Karamthulhu (unused NPC)"}, {"page_name_sub": "TzHaar-Ket-Rak", "id": ["10621", "10622"], "page_name": "TzHaar-Ket-Rak"}, {"page_name_sub": "Frog (Mount Quidamortem)", "id": ["479"], "page_name": "Frog (Mount Quidamortem)"}, {"page_name_sub": "Frog (Makeover Mage)", "id": ["3290"], "page_name": "Frog (Makeover Mage)"}, {"page_name_sub": "Dusuri", "id": ["10630", "10631"], "page_name": "Dusuri"}, {"page_name_sub": "Star Sprite", "id": ["10632"], "page_name": "Star Sprite"}, {"page_name_sub": "Tiny tempor", "id": ["10562", "10637"], "page_name": "Tiny tempor"}, {"page_name_sub": "Ferryman Sathwood", "id": ["10610"], "page_name": "Ferryman Sathwood"}, {"page_name_sub": "Gregg", "id": ["hist10638", "hist10639", "hist10640", "hist10641", "hist10642", "hist10643", "hist10646", "hist10647", "hist10648", "hist10649"], "page_name": "Gregg"}, {"page_name_sub": "Gita Prymes", "id": ["10613"], "page_name": "Gita Prymes"}, {"page_name_sub": "Koanee", "id": ["10615"], "page_name": "Koanee"}, {"page_name_sub": "Captain Pudi", "id": ["10583", "10585", "10586"], "page_name": "Captain Pudi"}, {"page_name_sub": "Ferryman Nathwood", "id": ["10611"], "page_name": "Ferryman Nathwood"}, {"page_name_sub": "Captain Dudi", "id": ["10584", "10587", "10588"], "page_name": "Captain Dudi"}, {"page_name_sub": "First Mate Deri", "id": ["10593", "10595"], "page_name": "First Mate Deri"}, {"page_name_sub": "First Mate Peri", "id": ["10596", "10597"], "page_name": "First Mate Peri"}, {"page_name_sub": "Cannoneer#Male", "id": ["10600", "10601"], "page_name": "Cannoneer"}, {"page_name_sub": "Cannoneer#Female", "id": ["10599", "10602"], "page_name": "Cannoneer"}, {"page_name_sub": "Fishing spot (Tempoross Cove)#Normal", "id": ["10565", " 10568"], "page_name": "Fishing spot (Tempoross Cove)"}, {"page_name_sub": "Fishing spot (Tempoross Cove)#Active", "id": ["10569"], "page_name": "Fishing spot (Tempoross Cove)"}, {"page_name_sub": "Timallus", "id": ["10616"], "page_name": "Timallus"}, {"page_name_sub": "Taiman", "id": ["10614"], "page_name": "Taiman"}, {"page_name_sub": "Lauretta", "id": ["10617"], "page_name": "Lauretta"}, {"page_name_sub": "Retired sailor", "id": ["10612"], "page_name": "Retired sailor"}, {"page_name_sub": "Ishmael", "id": ["10618"], "page_name": "Ishmael"}, {"page_name_sub": "Spirit Angler#1", "id": ["10606"], "page_name": "Spirit Angler"}, {"page_name_sub": "Spirit Angler#4", "id": ["10609"], "page_name": "Spirit Angler"}, {"page_name_sub": "Spirit Angler#3", "id": ["10608"], "page_name": "Spirit Angler"}, {"page_name_sub": "Spirit Angler#2", "id": ["10607"], "page_name": "Spirit Angler"}, {"page_name_sub": "Shantay Guard (Ruins of Unkah)", "id": ["10634"], "page_name": "Shantay Guard (Ruins of Unkah)"}, {"page_name_sub": "Sailor (Ruins of Unkah)", "id": ["10604"], "page_name": "Sailor (Ruins of Unkah)"}, {"page_name_sub": "Spirit pool#Inactive", "id": ["10570"], "page_name": "Spirit pool"}, {"page_name_sub": "Spirit pool#Active", "id": ["10571"], "page_name": "Spirit pool"}, {"page_name_sub": "Lightning cloud", "id": ["10580"], "page_name": "Lightning cloud"}, {"page_name_sub": "Ammunition crate", "id": ["10576", "10577", "10578", "10579"], "page_name": "Ammunition crate"}, {"page_name_sub": "Spirit Angler (Reward pool)", "id": ["10605"], "page_name": "Spirit Angler (Reward pool)"}, {"page_name_sub": "Cat (2021 Easter event)", "id": ["hist10644"], "page_name": "Cat (2021 Easter event)"}, {"page_name_sub": "Kitten (Gertrude's Cat)", "id": ["3498"], "page_name": "Kitten (Gertrude's Cat)"}, {"page_name_sub": "Marley#Before Quest", "id": ["10656"], "page_name": "Marley"}, {"page_name_sub": "Marley#After Quest", "id": ["10656"], "page_name": "Marley"}, {"page_name_sub": "Ramarno#After dialogue", "id": ["10684"], "page_name": "Ramarno"}, {"page_name_sub": "Ramarno#Before dialogue", "id": ["10685"], "page_name": "Ramarno"}, {"page_name_sub": "Checkal#Before Quest", "id": ["10657"], "page_name": "Checkal"}, {"page_name_sub": "Checkal#After Quest", "id": ["10657"], "page_name": "Checkal"}, {"page_name_sub": "Willow (Below Ice Mountain)#Before Quest", "id": ["10655", " 10661"], "page_name": "Willow (Below Ice Mountain)"}, {"page_name_sub": "Willow (Below Ice Mountain)#After Quest", "id": ["10655", " 10661"], "page_name": "Willow (Below Ice Mountain)"}, {"page_name_sub": "Body Golem#Golem", "id": ["10691"], "page_name": "Body Golem"}, {"page_name_sub": "Body Golem#Rubble", "id": ["10692"], "page_name": "Body Golem"}, {"page_name_sub": "Chaos Golem#Golem", "id": ["10689"], "page_name": "Chaos Golem"}, {"page_name_sub": "Chaos Golem#Rubble", "id": ["10690"], "page_name": "Chaos Golem"}, {"page_name_sub": "Flawed Golem#Golem", "id": ["10695"], "page_name": "Flawed Golem"}, {"page_name_sub": "Flawed Golem#Rubble", "id": ["10696"], "page_name": "Flawed Golem"}, {"page_name_sub": "Mind Golem#Golem", "id": ["10693"], "page_name": "Mind Golem"}, {"page_name_sub": "Mind Golem#Rubble", "id": ["10694"], "page_name": "Mind Golem"}, {"page_name_sub": "Burntof#Before Quest", "id": ["10659", "10660", "10664"], "page_name": "Burntof"}, {"page_name_sub": "Burntof#After Quest", "id": ["10659", "10660", "10664"], "page_name": "Burntof"}, {"page_name_sub": "Atlas", "id": ["10658"], "page_name": "Atlas"}, {"page_name_sub": "Ancient Guardian#Golem", "id": ["10654", "10665"], "page_name": "Ancient Guardian"}, {"page_name_sub": "Ancient Guardian#Rubble", "id": ["10666"], "page_name": "Ancient Guardian"}, {"page_name_sub": "Frog (Ruins of Camdozaal)", "id": ["10700"], "page_name": "Frog (Ruins of Camdozaal)"}, {"page_name_sub": "Vardorvis#Quest", "id": ["12224", "12228", "12425"], "page_name": "Vardorvis"}, {"page_name_sub": "Vardorvis#Awakened", "id": ["12223", "12426"], "page_name": "Vardorvis"}, {"page_name_sub": "Vardorvis#Post-quest", "id": ["12223", "12426"], "page_name": "Vardorvis"}, {"page_name_sub": "Ghost (Ruins of Camdozaal)#Hooded robes", "id": ["10699"], "page_name": "Ghost (Ruins of Camdozaal)"}, {"page_name_sub": "Ghost (Ruins of Camdozaal)#Female spy", "id": ["10698"], "page_name": "Ghost (Ruins of Camdozaal)"}, {"page_name_sub": "Ghost (Ruins of Camdozaal)#Male spy", "id": ["10697"], "page_name": "Ghost (Ruins of Camdozaal)"}, {"page_name_sub": "Fishing spot (Camdozaal)", "id": ["10686"], "page_name": "Fishing spot (Camdozaal)"}, {"page_name_sub": "Albatross", "id": ["15224"], "page_name": "Albatross"}, {"page_name_sub": "Albatross", "id": ["15225"], "page_name": "Albatross"}, {"page_name_sub": "Orc (historical)", "id": ["hist2832"], "page_name": "Orc (historical)"}, {"page_name_sub": "Goblin (historical)#Green (original)", "id": ["677"], "page_name": "Goblin (historical)"}, {"page_name_sub": "Goblin (historical)#Red (original)", "id": ["678"], "page_name": "Goblin (historical)"}, {"page_name_sub": "Goblin (historical)#Red (updated)", "id": ["3047"], "page_name": "Goblin (historical)"}, {"page_name_sub": "Goblin (historical)#Green (updated)", "id": ["3048"], "page_name": "Goblin (historical)"}, {"page_name_sub": "Santa (historical)", "id": ["hist3115"], "page_name": "Santa (historical)"}, {"page_name_sub": "Troll (historical)", "id": ["hist2833"], "page_name": "Troll (historical)"}, {"page_name_sub": "Forester (McGrubor's Wood)", "id": ["4076"], "page_name": "Forester (McGrubor's Wood)"}, {"page_name_sub": "Xamphur", "id": ["10954", "10955"], "page_name": "Xamphur"}, {"page_name_sub": "Xamphur", "id": ["10953", "10956"], "page_name": "Xamphur"}, {"page_name_sub": "Xamphur", "id": ["10951"], "page_name": "Xamphur"}, {"page_name_sub": "Knight of Ardougne (unused)", "id": ["3300"], "page_name": "Knight of Ardougne (unused)"}, {"page_name_sub": "Dryad (unused)", "id": ["2828"], "page_name": "Dryad (unused)"}, {"page_name_sub": "Sheep (Castle Wars)", "id": ["5726"], "page_name": "Sheep (Castle Wars)"}, {"page_name_sub": "Rabbit (Castle Wars)", "id": ["5727"], "page_name": "Rabbit (Castle Wars)"}, {"page_name_sub": "Imp (Castle Wars)", "id": ["5728"], "page_name": "Imp (Castle Wars)"}, {"page_name_sub": "Tyras guard (Catapult)", "id": ["8762"], "page_name": "Tyras guard (Catapult)"}, {"page_name_sub": "Jig cart#Cooled", "id": ["5226"], "page_name": "Jig cart"}, {"page_name_sub": "Jig cart#Quenched", "id": ["5225"], "page_name": "Jig cart"}, {"page_name_sub": "Jig cart#Elemental metal", "id": ["5222"], "page_name": "Jig cart"}, {"page_name_sub": "Jig cart#Heated", "id": ["5223"], "page_name": "Jig cart"}, {"page_name_sub": "Jig cart#Empty", "id": ["5221"], "page_name": "Jig cart"}, {"page_name_sub": "Jig cart#Pressed", "id": ["5224"], "page_name": "Jig cart"}, {"page_name_sub": "Zamorakian recruiter", "id": ["10732"], "page_name": "Zamorakian recruiter"}, {"page_name_sub": "Saradominist recruiter", "id": ["8644"], "page_name": "Saradominist recruiter"}, {"page_name_sub": "Meredith", "id": ["10733"], "page_name": "Meredith"}, {"page_name_sub": "Goblin (Goblin Village)#Green", "id": ["662", "663", "664", "665", "666", "667", "668"], "page_name": "Goblin (Goblin Village)"}, {"page_name_sub": "Goblin (Goblin Village)#Red", "id": ["655", "656", "657", "658", "659", "660", "661"], "page_name": "Goblin (Goblin Village)"}, {"page_name_sub": "Goblin (Vault of War)#Level 5", "id": ["2484"], "page_name": "Goblin (Vault of War)"}, {"page_name_sub": "Goblin (Vault of War)#Level 16", "id": ["2487", "2489"], "page_name": "Goblin (Vault of War)"}, {"page_name_sub": "Goblin (Vault of War)#Level 25", "id": ["2488"], "page_name": "Goblin (Vault of War)"}, {"page_name_sub": "Goblin (Vault of War)#Level 11", "id": ["2486"], "page_name": "Goblin (Vault of War)"}, {"page_name_sub": "Goblin (Vault of War)#Level 13", "id": ["2485"], "page_name": "Goblin (Vault of War)"}, {"page_name_sub": "Goblin (God Wars Dungeon)#Level 12", "id": ["2246"], "page_name": "Goblin (God Wars Dungeon)"}, {"page_name_sub": "Goblin (God Wars Dungeon)#Level 15", "id": ["2248"], "page_name": "Goblin (God Wars Dungeon)"}, {"page_name_sub": "Goblin (God Wars Dungeon)#Level 17", "id": ["2245"], "page_name": "Goblin (God Wars Dungeon)"}, {"page_name_sub": "Goblin (God Wars Dungeon)#Level 13", "id": ["2249"], "page_name": "Goblin (God Wars Dungeon)"}, {"page_name_sub": "Goblin (God Wars Dungeon)#Level 12 (banner)", "id": ["2247"], "page_name": "Goblin (God Wars Dungeon)"}, {"page_name_sub": "Ghost (Grave of Scorpius)", "id": ["5370"], "page_name": "Ghost (Grave of Scorpius)"}, {"page_name_sub": "Supporting Pillar", "id": ["8379", "10840", "10857"], "page_name": "Supporting Pillar"}, {"page_name_sub": "Supporting Pillar#Collapsing", "id": ["8377", "10838", "10855"], "page_name": "Supporting Pillar"}, {"page_name_sub": "Supporting Pillar#Fading", "id": ["8378", "10839", "10856"], "page_name": "Supporting Pillar"}, {"page_name_sub": "Energy focus#Red", "id": ["7581"], "page_name": "Energy focus"}, {"page_name_sub": "Energy focus#Green", "id": ["7582"], "page_name": "Energy focus"}, {"page_name_sub": "Energy focus#Blue", "id": ["7583"], "page_name": "Energy focus"}, {"page_name_sub": "Energy focus#White", "id": ["7580"], "page_name": "Energy focus"}, {"page_name_sub": "Queen Zyanyi Arkan#With Ikniu", "id": ["11012", "13695"], "page_name": "Queen Zyanyi Arkan"}, {"page_name_sub": "Queen Zyanyi Arkan#Throne", "id": ["14296"], "page_name": "Queen Zyanyi Arkan"}, {"page_name_sub": "Queen Zyanyi Arkan#Without Ikniu", "id": ["14287", "14288", "14294", "14297", "14373"], "page_name": "Queen Zyanyi Arkan"}, {"page_name_sub": "Queen Zyanyi Arkan#Armed", "id": ["14289", "14290", "14291", "14292", "14389", "14396", "14469"], "page_name": "Queen Zyanyi Arkan"}, {"page_name_sub": "Poacher#1", "id": ["12553", "12556"], "page_name": "Poacher"}, {"page_name_sub": "Poacher#3", "id": ["12555", "12558"], "page_name": "Poacher"}, {"page_name_sub": "Poacher#2", "id": ["12554", "12557", ""], "page_name": "Poacher"}, {"page_name_sub": "Clerk (Clan Hub)", "id": ["10759"], "page_name": "Clerk (Clan Hub)"}, {"page_name_sub": "Snowman", "id": ["hist2586"], "page_name": "Snowman"}, {"page_name_sub": "Bobbing fossil", "id": ["7779"], "page_name": "Bobbing fossil"}, {"page_name_sub": "Egg launcher", "id": ["5777", "5778"], "page_name": "Egg launcher"}, {"page_name_sub": "Raqueel#Purple", "id": ["10746"], "page_name": "Raqueel"}, {"page_name_sub": "Raqueel#Black", "id": ["10739"], "page_name": "Raqueel"}, {"page_name_sub": "Raqueel#Blue", "id": ["10741"], "page_name": "Raqueel"}, {"page_name_sub": "Raqueel#Green", "id": ["10743"], "page_name": "Raqueel"}, {"page_name_sub": "Raqueel#Light blue", "id": ["10745"], "page_name": "Raqueel"}, {"page_name_sub": "Raqueel#Yellow", "id": ["10744"], "page_name": "Raqueel"}, {"page_name_sub": "Raqueel#Orange", "id": ["10740"], "page_name": "Raqueel"}, {"page_name_sub": "Raqueel#Red", "id": ["10742"], "page_name": "Raqueel"}, {"page_name_sub": "Gem (Clan Hall)#Purple", "id": ["10755"], "page_name": "Gem (Clan Hall)"}, {"page_name_sub": "Gem (Clan Hall)#Black", "id": ["10748"], "page_name": "Gem (Clan Hall)"}, {"page_name_sub": "Gem (Clan Hall)#Blue", "id": ["10750"], "page_name": "Gem (Clan Hall)"}, {"page_name_sub": "Gem (Clan Hall)#Green", "id": ["10752"], "page_name": "Gem (Clan Hall)"}, {"page_name_sub": "Gem (Clan Hall)#Light blue", "id": ["10754"], "page_name": "Gem (Clan Hall)"}, {"page_name_sub": "Gem (Clan Hall)#Yellow", "id": ["10753"], "page_name": "Gem (Clan Hall)"}, {"page_name_sub": "Gem (Clan Hall)#Orange", "id": ["10749"], "page_name": "Gem (Clan Hall)"}, {"page_name_sub": "Gem (Clan Hall)#Red", "id": ["10751"], "page_name": "Gem (Clan Hall)"}, {"page_name_sub": "Hannibal", "id": ["11651"], "page_name": "Hannibal"}, {"page_name_sub": "Gardener Jay Jr.#Gardening trowel", "id": ["10756"], "page_name": "Gardener Jay Jr."}, {"page_name_sub": "Gardener Jay Jr.#Rake", "id": ["10757"], "page_name": "Gardener Jay Jr."}, {"page_name_sub": "Gardener Jay Jr.#Watering can", "id": ["10758"], "page_name": "Gardener Jay Jr."}, {"page_name_sub": "Enormous Tentacle (Fishing Trawler)#Idle", "id": ["10709"], "page_name": "Enormous Tentacle (Fishing Trawler)"}, {"page_name_sub": "Enormous Tentacle (Fishing Trawler)#Swinging", "id": ["10708"], "page_name": "Enormous Tentacle (Fishing Trawler)"}, {"page_name_sub": "Nylocas Prinkipas#Ranged", "id": ["10806"], "page_name": "Nylocas Prinkipas"}, {"page_name_sub": "Nylocas Prinkipas#Magic", "id": ["10805"], "page_name": "Nylocas Prinkipas"}, {"page_name_sub": "Nylocas Prinkipas#Melee", "id": ["10803", "10804"], "page_name": "Nylocas Prinkipas"}, {"page_name_sub": "Skeleton (Wrath Altar)", "id": ["8139"], "page_name": "Skeleton (Wrath Altar)"}, {"page_name_sub": "Zombie Thrall (beta)", "id": ["hist10716"], "page_name": "Zombie Thrall (beta)"}, {"page_name_sub": "Ghostly thrall (beta)", "id": ["beta10714"], "page_name": "Ghostly thrall (beta)"}, {"page_name_sub": "Skeletal thrall (beta)", "id": ["beta10715"], "page_name": "Skeletal thrall (beta)"}, {"page_name_sub": "Lesser ghostly thrall", "id": ["10878"], "page_name": "Lesser ghostly thrall"}, {"page_name_sub": "Lesser skeletal thrall", "id": ["10881"], "page_name": "Lesser skeletal thrall"}, {"page_name_sub": "Lesser zombified thrall", "id": ["10884"], "page_name": "Lesser zombified thrall"}, {"page_name_sub": "Superior ghostly thrall", "id": ["10879"], "page_name": "Superior ghostly thrall"}, {"page_name_sub": "Greater ghostly thrall", "id": ["10880"], "page_name": "Greater ghostly thrall"}, {"page_name_sub": "Superior skeletal thrall", "id": ["10882"], "page_name": "Superior skeletal thrall"}, {"page_name_sub": "Greater skeletal thrall", "id": ["10883"], "page_name": "Greater skeletal thrall"}, {"page_name_sub": "Superior zombified thrall", "id": ["10885"], "page_name": "Superior zombified thrall"}, {"page_name_sub": "Greater zombified thrall", "id": ["10886"], "page_name": "Greater zombified thrall"}, {"page_name_sub": "Necromancer (Great Kourend)", "id": ["11088"], "page_name": "Necromancer (Great Kourend)"}, {"page_name_sub": "Kualti#Hammer", "id": ["11014", "14367"], "page_name": "Kualti"}, {"page_name_sub": "Kualti#Hasta", "id": ["11017", "14371"], "page_name": "Kualti"}, {"page_name_sub": "Kualti#Axe", "id": ["11015", "14372"], "page_name": "Kualti"}, {"page_name_sub": "Kualti#Sword", "id": ["11018", "14370"], "page_name": "Kualti"}, {"page_name_sub": "Kualti#Cutlass", "id": ["11013", "14368"], "page_name": "Kualti"}, {"page_name_sub": "Kualti#Flail", "id": ["11016", "14369"], "page_name": "Kualti"}, {"page_name_sub": "Lynx#Level 24", "id": ["11069"], "page_name": "Lynx"}, {"page_name_sub": "Lynx#Level 21", "id": ["11068"], "page_name": "Lynx"}, {"page_name_sub": "Blair", "id": ["11040"], "page_name": "Blair"}, {"page_name_sub": "Robyn", "id": ["11042"], "page_name": "Robyn"}, {"page_name_sub": "Daryl", "id": ["11041"], "page_name": "Daryl"}, {"page_name_sub": "Boar#Level 5", "id": ["11066"], "page_name": "Boar"}, {"page_name_sub": "Boar#Level 7", "id": ["11067"], "page_name": "Boar"}, {"page_name_sub": "Judge of Yama (A Kingdom Divided)", "id": ["10936", "10938"], "page_name": "Judge of Yama (A Kingdom Divided)"}, {"page_name_sub": "Phantom Hand#Left Hand", "id": ["10957"], "page_name": "Phantom Hand"}, {"page_name_sub": "Phantom Hand#Right Hand", "id": ["10958"], "page_name": "Phantom Hand"}, {"page_name_sub": "Drunken soldier", "id": ["11048"], "page_name": "Drunken soldier"}, {"page_name_sub": "Assassin (A Kingdom Divided)", "id": ["10940"], "page_name": "Assassin (A Kingdom Divided)"}, {"page_name_sub": "Assassin (A Kingdom Divided)", "id": ["10941"], "page_name": "Assassin (A Kingdom Divided)"}, {"page_name_sub": "Assassin (A Kingdom Divided)", "id": ["10942"], "page_name": "Assassin (A Kingdom Divided)"}, {"page_name_sub": "Barbarian Warlord", "id": ["10989"], "page_name": "Barbarian Warlord"}, {"page_name_sub": "Father Eysseric", "id": ["11050"], "page_name": "Father Eysseric"}, {"page_name_sub": "Lynx Tamer", "id": ["11071"], "page_name": "Lynx Tamer"}, {"page_name_sub": "Kaston", "id": ["11055"], "page_name": "Kaston"}, {"page_name_sub": "Elijah", "id": ["11052"], "page_name": "Elijah"}, {"page_name_sub": "Captain Bruce", "id": ["11060"], "page_name": "Captain Bruce"}, {"page_name_sub": "Old man (Shayzien)", "id": ["11056"], "page_name": "Old man (Shayzien)"}, {"page_name_sub": "Cabin Boy Herbert", "id": ["10932", "10933", "10934"], "page_name": "Cabin Boy Herbert"}, {"page_name_sub": "Farolt", "id": ["11090"], "page_name": "Farolt"}, {"page_name_sub": "Commissioner Anwar", "id": ["11059"], "page_name": "Commissioner Anwar"}, {"page_name_sub": "Sergeant Ricardo", "id": ["11061"], "page_name": "Sergeant Ricardo"}, {"page_name_sub": "Jessie", "id": ["11062"], "page_name": "Jessie"}, {"page_name_sub": "Sheryl", "id": ["11044"], "page_name": "Sheryl"}, {"page_name_sub": "Oswald", "id": ["11043"], "page_name": "Oswald"}, {"page_name_sub": "Mia", "id": ["11051"], "page_name": "Mia"}, {"page_name_sub": "Barbarian (Barbarian Camp)#Level 9", "id": ["10988"], "page_name": "Barbarian (Barbarian Camp)"}, {"page_name_sub": "Barbarian (Barbarian Camp)#Level 10 (spear)", "id": ["10987"], "page_name": "Barbarian (Barbarian Camp)"}, {"page_name_sub": "Barbarian (Barbarian Camp)#Level 15", "id": ["10986"], "page_name": "Barbarian (Barbarian Camp)"}, {"page_name_sub": "Barbarian (Barbarian Camp)#Level 10 (greataxe)", "id": ["10985"], "page_name": "Barbarian (Barbarian Camp)"}, {"page_name_sub": "Barbarian (Barbarian Camp)#Level 10 (2h sword)", "id": ["10984"], "page_name": "Barbarian (Barbarian Camp)"}, {"page_name_sub": "Sheep (Big Cats & WWF)#1", "id": ["hist5870"], "page_name": "Sheep (Big Cats & WWF)"}, {"page_name_sub": "Sheep (Big Cats & WWF)#3", "id": ["hist5872"], "page_name": "Sheep (Big Cats & WWF)"}, {"page_name_sub": "Sheep (Big Cats & WWF)#2", "id": ["hist5871"], "page_name": "Sheep (Big Cats & WWF)"}, {"page_name_sub": "Sergeant (Kebos Lowlands)", "id": ["8600", "10505", "10725"], "page_name": "Sergeant (Kebos Lowlands)"}, {"page_name_sub": "Soldier (recruits)#Tier 1 (male)", "id": ["6883", "6884", "6885"], "page_name": "Soldier (recruits)"}, {"page_name_sub": "Soldier (recruits)#Tier 2 (female)", "id": ["6892", "6893", "6894"], "page_name": "Soldier (recruits)"}, {"page_name_sub": "Soldier (recruits)#Tier 2 (male)", "id": ["6889", "6890", "6891"], "page_name": "Soldier (recruits)"}, {"page_name_sub": "Soldier (recruits)#Tier 1 (female)", "id": ["6886", "6887", "6888"], "page_name": "Soldier (recruits)"}, {"page_name_sub": "Bandit (Shayzien)", "id": ["11063", "11064", "11065"], "page_name": "Bandit (Shayzien)"}, {"page_name_sub": "Soldier (Kebos Lowlands)", "id": ["8599"], "page_name": "Soldier (Kebos Lowlands)"}, {"page_name_sub": "Soldier (The Cloak and Stagger)#Female", "id": ["11046"], "page_name": "Soldier (The Cloak and Stagger)"}, {"page_name_sub": "Soldier (The Cloak and Stagger)#Male", "id": ["11047"], "page_name": "Soldier (The Cloak and Stagger)"}, {"page_name_sub": "Guard (2014 Goblin Invasion, spy)", "id": ["hist6718", "hist6719", "hist6720", "hist6721", "hist6722", "hist6723"], "page_name": "Guard (2014 Goblin Invasion, spy)"}, {"page_name_sub": "Goblin (2014 Goblin Invasion, spy)#Level 12", "id": ["hist6716", "hist6717"], "page_name": "Goblin (2014 Goblin Invasion, spy)"}, {"page_name_sub": "Goblin (2014 Goblin Invasion, spy)#Level 11", "id": ["hist6712", "hist6713"], "page_name": "Goblin (2014 Goblin Invasion, spy)"}, {"page_name_sub": "Goblin (2014 Goblin Invasion, spy)#Level 14", "id": ["hist6714", "hist6715"], "page_name": "Goblin (2014 Goblin Invasion, spy)"}, {"page_name_sub": "Goblin (2014 Goblin Invasion)", "id": ["hist6700"], "page_name": "Goblin (2014 Goblin Invasion)"}, {"page_name_sub": "Guard (2014 Goblin Invasion)", "id": ["hist6706"], "page_name": "Guard (2014 Goblin Invasion)"}, {"page_name_sub": "Protest Leader", "id": ["10896"], "page_name": "Protest Leader"}, {"page_name_sub": "Deckchair", "id": ["hist14157"], "page_name": "Deckchair"}, {"page_name_sub": "Drain Pipe", "id": ["5122"], "page_name": "Drain Pipe"}, {"page_name_sub": "Dusty Aliv", "id": ["11161"], "page_name": "Dusty Aliv"}, {"page_name_sub": "Araxyte#Level 146", "id": ["11176", "13667"], "page_name": "Araxyte"}, {"page_name_sub": "Araxyte#Level 96", "id": ["11175", "13666"], "page_name": "Araxyte"}, {"page_name_sub": "Nylocas Queen", "id": ["11181"], "page_name": "Nylocas Queen"}, {"page_name_sub": "Hespori (A Night at the Theatre)", "id": ["11192"], "page_name": "Hespori (A Night at the Theatre)"}, {"page_name_sub": "The Sage (Shattered Relics League)", "id": ["11232"], "page_name": "The Sage (Shattered Relics League)"}, {"page_name_sub": "Osmumten#Spirit", "id": ["11691"], "page_name": "Osmumten"}, {"page_name_sub": "Osmumten#Osmumten", "id": ["11689", "11690", "11692", "11693"], "page_name": "Osmumten"}, {"page_name_sub": "Eye (Abyssal Nexus)", "id": ["6479", "6480"], "page_name": "Eye (Abyssal Nexus)"}, {"page_name_sub": "Void Knight (Pest Control)#1", "id": ["2950"], "page_name": "Void Knight (Pest Control)"}, {"page_name_sub": "Void Knight (Pest Control)#4", "id": ["2953"], "page_name": "Void Knight (Pest Control)"}, {"page_name_sub": "Void Knight (Pest Control)#3", "id": ["2952"], "page_name": "Void Knight (Pest Control)"}, {"page_name_sub": "Void Knight (Pest Control)#2", "id": ["2951"], "page_name": "Void Knight (Pest Control)"}, {"page_name_sub": "Chair (The Slug Menace)", "id": ["2832"], "page_name": "Chair (The Slug Menace)"}, {"page_name_sub": "Sourhog (A Porcine of Interest)", "id": ["10436"], "page_name": "Sourhog (A Porcine of Interest)"}, {"page_name_sub": "Sourhog (A Porcine of Interest)", "id": ["10437"], "page_name": "Sourhog (A Porcine of Interest)"}, {"page_name_sub": "Strange Device (Tale of the Righteous)", "id": ["7598"], "page_name": "Strange Device (Tale of the Righteous)"}, {"page_name_sub": "Tsunami", "id": ["8099"], "page_name": "Tsunami"}, {"page_name_sub": "Secretary", "id": ["5989"], "page_name": "Secretary"}, {"page_name_sub": "Saboteur", "id": ["1237"], "page_name": "Saboteur"}, {"page_name_sub": "Tin ore (Blast Furnace)", "id": ["2924"], "page_name": "Tin ore (Blast Furnace)"}, {"page_name_sub": "Blasted ore (NPC)", "id": ["7074"], "page_name": "Blasted ore (NPC)"}, {"page_name_sub": "Copper ore (Blast Furnace)", "id": ["2925"], "page_name": "Copper ore (Blast Furnace)"}, {"page_name_sub": "Iron ore (Blast Furnace)", "id": ["2926"], "page_name": "Iron ore (Blast Furnace)"}, {"page_name_sub": "Mithril ore (Blast Furnace)", "id": ["2927"], "page_name": "Mithril ore (Blast Furnace)"}, {"page_name_sub": "Adamantite ore (Blast Furnace)", "id": ["2928"], "page_name": "Adamantite ore (Blast Furnace)"}, {"page_name_sub": "Runite ore (Blast Furnace)", "id": ["2929"], "page_name": "Runite ore (Blast Furnace)"}, {"page_name_sub": "Silver ore (Blast Furnace)", "id": ["2930"], "page_name": "Silver ore (Blast Furnace)"}, {"page_name_sub": "Gold ore (Blast Furnace)", "id": ["2931"], "page_name": "Gold ore (Blast Furnace)"}, {"page_name_sub": "Perfect gold ore (Blast Furnace)", "id": ["2933"], "page_name": "Perfect gold ore (Blast Furnace)"}, {"page_name_sub": "Coal (Blast Furnace)", "id": ["2932"], "page_name": "Coal (Blast Furnace)"}, {"page_name_sub": "Oddskull (NPC)", "id": ["4187"], "page_name": "Oddskull (NPC)"}, {"page_name_sub": "Evil Chicken (Recipe for Disaster)", "id": ["1870"], "page_name": "Evil Chicken (Recipe for Disaster)"}, {"page_name_sub": "Bench (What Lies Below)", "id": ["4178"], "page_name": "Bench (What Lies Below)"}, {"page_name_sub": "HAM member (Death to the Dorgeshuun)", "id": ["4327"], "page_name": "HAM member (Death to the Dorgeshuun)"}, {"page_name_sub": "Fire Wave (Judge of Yama)", "id": ["10939"], "page_name": "Fire Wave (Judge of Yama)"}, {"page_name_sub": "Floki", "id": ["9195"], "page_name": "Floki"}, {"page_name_sub": "Scythe (2013 Rare Drops)", "id": ["hist2296"], "page_name": "Scythe (2013 Rare Drops)"}, {"page_name_sub": "Pumpkin (2013 Rare Drops)", "id": ["hist2298"], "page_name": "Pumpkin (2013 Rare Drops)"}, {"page_name_sub": "Red h'ween Mask (2013 Rare Drops)", "id": ["hist2300"], "page_name": "Red h'ween Mask (2013 Rare Drops)"}, {"page_name_sub": "Blue h'ween Mask (2013 Rare Drops)", "id": ["hist6233"], "page_name": "Blue h'ween Mask (2013 Rare Drops)"}, {"page_name_sub": "Green h'ween Mask (2013 Rare Drops)", "id": ["hist6234"], "page_name": "Green h'ween Mask (2013 Rare Drops)"}, {"page_name_sub": "Skeleton outfit (2013 Rare Drops)", "id": ["hist6235"], "page_name": "Skeleton outfit (2013 Rare Drops)"}, {"page_name_sub": "Jack lantern mask (2013 Rare Drops)", "id": ["hist6236"], "page_name": "Jack lantern mask (2013 Rare Drops)"}, {"page_name_sub": "Yo-yo (2013 Rare Drops)", "id": ["hist6237"], "page_name": "Yo-yo (2013 Rare Drops)"}, {"page_name_sub": "Red partyhat (2013 Rare Drops)", "id": ["hist6238"], "page_name": "Red partyhat (2013 Rare Drops)"}, {"page_name_sub": "Yellow partyhat (2013 Rare Drops)", "id": ["hist6239"], "page_name": "Yellow partyhat (2013 Rare Drops)"}, {"page_name_sub": "Blue partyhat (2013 Rare Drops)", "id": ["hist6240"], "page_name": "Blue partyhat (2013 Rare Drops)"}, {"page_name_sub": "Green partyhat (2013 Rare Drops)", "id": ["hist6241"], "page_name": "Green partyhat (2013 Rare Drops)"}, {"page_name_sub": "Purple partyhat (2013 Rare Drops)", "id": ["hist6242"], "page_name": "Purple partyhat (2013 Rare Drops)"}, {"page_name_sub": "White partyhat (2013 Rare Drops)", "id": ["hist6243"], "page_name": "White partyhat (2013 Rare Drops)"}, {"page_name_sub": "Bunny ears (2013 Rare Drops)", "id": ["hist6244"], "page_name": "Bunny ears (2013 Rare Drops)"}, {"page_name_sub": "Reindeer hat (2013 Rare Drops)", "id": ["hist6245"], "page_name": "Reindeer hat (2013 Rare Drops)"}, {"page_name_sub": "Easter egg (2013 Rare Drops)", "id": ["hist6246"], "page_name": "Easter egg (2013 Rare Drops)"}, {"page_name_sub": "Guard (Port Sarim, sleeping)", "id": ["1551"], "page_name": "Guard (Port Sarim, sleeping)"}, {"page_name_sub": "Easter ring (2013 Rare Drops)", "id": ["hist6247"], "page_name": "Easter ring (2013 Rare Drops)"}, {"page_name_sub": "Marionette set (2013 Rare Drops)", "id": ["hist6248"], "page_name": "Marionette set (2013 Rare Drops)"}, {"page_name_sub": "Santa hat (2013 Rare Drops)", "id": ["hist6249"], "page_name": "Santa hat (2013 Rare Drops)"}, {"page_name_sub": "Wintumber tree (2013 Rare Drops)", "id": ["hist6250"], "page_name": "Wintumber tree (2013 Rare Drops)"}, {"page_name_sub": "Rubber chicken (2013 Rare Drops)", "id": ["hist6251"], "page_name": "Rubber chicken (2013 Rare Drops)"}, {"page_name_sub": "Hats & scarves (2013 Rare Drops)", "id": ["hist6252"], "page_name": "Hats & scarves (2013 Rare Drops)"}, {"page_name_sub": "Disk of Returning (2013 Rare Drops)", "id": ["hist6253"], "page_name": "Disk of Returning (2013 Rare Drops)"}, {"page_name_sub": "Chicken suit (2013 Rare Drops)", "id": ["hist6254"], "page_name": "Chicken suit (2013 Rare Drops)"}, {"page_name_sub": "Zombie head (2013 Rare Drops)", "id": ["hist6255"], "page_name": "Zombie head (2013 Rare Drops)"}, {"page_name_sub": "Half full wine jug (2013 Rare Drops)", "id": ["hist6256"], "page_name": "Half full wine jug (2013 Rare Drops)"}, {"page_name_sub": "Christmas cracker (2013 Rare Drops)", "id": ["hist6257"], "page_name": "Christmas cracker (2013 Rare Drops)"}, {"page_name_sub": "War ship (2013 Rare Drops)", "id": ["hist6258"], "page_name": "War ship (2013 Rare Drops)"}, {"page_name_sub": "Soldier (Shayzien, historical)#1", "id": ["6878"], "page_name": "Soldier (Shayzien, historical)"}, {"page_name_sub": "Soldier (Shayzien, historical)#3", "id": ["6880"], "page_name": "Soldier (Shayzien, historical)"}, {"page_name_sub": "Soldier (Shayzien, historical)#2", "id": ["6879"], "page_name": "Soldier (Shayzien, historical)"}, {"page_name_sub": "D3ad1i F15her", "id": ["11225"], "page_name": "D3ad1i F15her"}, {"page_name_sub": "Boar31337Killer", "id": ["11226"], "page_name": "Boar31337Killer"}, {"page_name_sub": "R0ck 5masher", "id": ["11228"], "page_name": "R0ck 5masher"}, {"page_name_sub": "Regent", "id": ["11229"], "page_name": "Regent"}, {"page_name_sub": "Group Storage tutor", "id": ["11230"], "page_name": "Group Storage tutor"}, {"page_name_sub": "Group Ironman tutor", "id": ["11231"], "page_name": "Group Ironman tutor"}, {"page_name_sub": "Enraged Boar", "id": ["11227"], "page_name": "Enraged Boar"}, {"page_name_sub": "Acorn (NPC)", "id": ["9415"], "page_name": "Acorn (NPC)"}, {"page_name_sub": "Small ninja monkey", "id": ["1462"], "page_name": "Small ninja monkey"}, {"page_name_sub": "Medium ninja monkey", "id": ["1463"], "page_name": "Medium ninja monkey"}, {"page_name_sub": "Gorilla (NPC)", "id": ["1464"], "page_name": "Gorilla (NPC)"}, {"page_name_sub": "Bearded gorilla", "id": ["1465"], "page_name": "Bearded gorilla"}, {"page_name_sub": "Ancient monkey", "id": ["1466"], "page_name": "Ancient monkey"}, {"page_name_sub": "Small zombie monkey", "id": ["1467"], "page_name": "Small zombie monkey"}, {"page_name_sub": "Large zombie monkey", "id": ["1468"], "page_name": "Large zombie monkey"}, {"page_name_sub": "Crust of ice", "id": ["3573"], "page_name": "Crust of ice"}, {"page_name_sub": "Furnace grate", "id": ["3574"], "page_name": "Furnace grate"}, {"page_name_sub": "Storm cloud (Zanaris)", "id": ["5834"], "page_name": "Storm cloud (Zanaris)"}, {"page_name_sub": "Cavemouth", "id": ["3334"], "page_name": "Cavemouth"}, {"page_name_sub": "Buinn", "id": ["2449"], "page_name": "Buinn"}, {"page_name_sub": "Thistle (Trollheim)", "id": ["4767"], "page_name": "Thistle (Trollheim)"}, {"page_name_sub": "Combat Test#Standard", "id": ["6802"], "page_name": "Combat Test"}, {"page_name_sub": "Combat Test#Maxhit", "id": ["8479"], "page_name": "Combat Test"}, {"page_name_sub": "Sigmund and Zanik", "id": ["5160"], "page_name": "Sigmund and Zanik"}, {"page_name_sub": "Jury", "id": ["4334"], "page_name": "Jury"}, {"page_name_sub": "Black demon (The Grand Tree)", "id": ["1432"], "page_name": "Black demon (The Grand Tree)"}, {"page_name_sub": "Looming shadow", "id": ["7116"], "page_name": "Looming shadow"}, {"page_name_sub": "Arc test#1", "id": ["8539"], "page_name": "Arc test"}, {"page_name_sub": "Arc test#2", "id": ["8540"], "page_name": "Arc test"}, {"page_name_sub": "Armoured Foe", "id": ["7750"], "page_name": "Armoured Foe"}, {"page_name_sub": "Well-armed Foe", "id": ["7751"], "page_name": "Well-armed Foe"}, {"page_name_sub": "Nylocas (A Night at the Theatre)", "id": ["11182"], "page_name": "Nylocas (A Night at the Theatre)"}, {"page_name_sub": "Crystal Whirlwind", "id": ["8921"], "page_name": "Crystal Whirlwind"}, {"page_name_sub": "Richard Flintmaul", "id": ["8562"], "page_name": "Richard Flintmaul"}, {"page_name_sub": "Snow (Wintertodt)", "id": ["7383"], "page_name": "Snow (Wintertodt)"}, {"page_name_sub": "Mourner (Biohazard)#West Ardougne 2", "id": ["9000"], "page_name": "Mourner (Biohazard)"}, {"page_name_sub": "Mourner (Biohazard)#Mourner Headquarters 2", "id": ["9009"], "page_name": "Mourner (Biohazard)"}, {"page_name_sub": "Mourner (Biohazard)#West Ardougne 3", "id": ["9003"], "page_name": "Mourner (Biohazard)"}, {"page_name_sub": "Mourner (Biohazard)#Mourner Headquarters 1", "id": ["9007"], "page_name": "Mourner (Biohazard)"}, {"page_name_sub": "Mourner (Biohazard)#Mourner Headquarters door", "id": ["9004"], "page_name": "Mourner (Biohazard)"}, {"page_name_sub": "Mourner (Biohazard)#Watchtower", "id": ["9010"], "page_name": "Mourner (Biohazard)"}, {"page_name_sub": "Mourner (Biohazard)#West Ardougne 1", "id": ["8999"], "page_name": "Mourner (Biohazard)"}, {"page_name_sub": "Mourner (Plague City)#West Ardougne", "id": ["8970"], "page_name": "Mourner (Plague City)"}, {"page_name_sub": "Mourner (Plague City)#East Ardougne", "id": ["8971"], "page_name": "Mourner (Plague City)"}, {"page_name_sub": "Mourner (Plague City)#Quarantined house", "id": ["8975"], "page_name": "Mourner (Plague City)"}, {"page_name_sub": "Mourner (Plague City)#Ardougne Wall", "id": ["8972"], "page_name": "Mourner (Plague City)"}, {"page_name_sub": "Mourner (Mourner Tunnels)#Headquarters", "id": ["9018"], "page_name": "Mourner (Mourner Tunnels)"}, {"page_name_sub": "Mourner (Mourner Tunnels)#Tunnels", "id": ["8771"], "page_name": "Mourner (Mourner Tunnels)"}, {"page_name_sub": "Mourner (Song of the Elves)#Level 24", "id": ["8844"], "page_name": "Mourner (Song of the Elves)"}, {"page_name_sub": "Mourner (Song of the Elves)#Level 51", "id": ["8845"], "page_name": "Mourner (Song of the Elves)"}, {"page_name_sub": "Mourner (Song of the Elves)#Level 106", "id": ["8846"], "page_name": "Mourner (Song of the Elves)"}, {"page_name_sub": "Mourner (boss)", "id": ["9008"], "page_name": "Mourner (boss)"}, {"page_name_sub": "Ned (historical)", "id": ["hist818"], "page_name": "Ned (historical)"}, {"page_name_sub": "Xi plzPetDogz xiX#2022 Easter event", "id": ["hist11465", "hist11466"], "page_name": "Xi plzPetDogz xiX"}, {"page_name_sub": "Xi plzPetDogz xiX#2021 Christmas event", "id": ["hist11259"], "page_name": "Xi plzPetDogz xiX"}, {"page_name_sub": "Xi plzPetDogz xiX#2021 Halloween event", "id": ["hist11254"], "page_name": "Xi plzPetDogz xiX"}, {"page_name_sub": "Monk (2021 Halloween event)", "id": ["hist11233", "hist11255"], "page_name": "Monk (2021 Halloween event)"}, {"page_name_sub": "Ghost (Soul Wars)", "id": ["10538"], "page_name": "Ghost (Soul Wars)"}, {"page_name_sub": "Oziach (2021 Halloween event)#1", "id": ["hist11236", "hist11257"], "page_name": "Oziach (2021 Halloween event)"}, {"page_name_sub": "Oziach (2021 Halloween event)#3", "id": ["hist11241"], "page_name": "Oziach (2021 Halloween event)"}, {"page_name_sub": "Oziach (2021 Halloween event)#2", "id": ["hist11237", "hist11258"], "page_name": "Oziach (2021 Halloween event)"}, {"page_name_sub": "Estate agent (2021 Halloween event)#Cutscenes", "id": ["hist11242"], "page_name": "Estate agent (2021 Halloween event)"}, {"page_name_sub": "Estate agent (2021 Halloween event)#Overworld", "id": ["hist11238", "hist11259"], "page_name": "Estate agent (2021 Halloween event)"}, {"page_name_sub": "Pizazz Hat", "id": ["7512"], "page_name": "Pizazz Hat"}, {"page_name_sub": "Rocking chair (2021 Halloween event)", "id": ["hist11262"], "page_name": "Rocking chair (2021 Halloween event)"}, {"page_name_sub": "Iffie (2021 Halloween event)#Thessalia's Fine Clothes.", "id": ["hist11232"], "page_name": "Iffie (2021 Halloween event)"}, {"page_name_sub": "Iffie (2021 Halloween event)#Blue Moon Inn (kitchen)", "id": ["hist11246"], "page_name": "Iffie (2021 Halloween event)"}, {"page_name_sub": "Iffie (2021 Halloween event)#Edgeville Monastery", "id": ["hist11240", "hist11261"], "page_name": "Iffie (2021 Halloween event)"}, {"page_name_sub": "Iffie (2021 Halloween event)#Blue Moon Inn", "id": ["hist11239", "hist11260", "hist11245"], "page_name": "Iffie (2021 Halloween event)"}, {"page_name_sub": "Brother Jered (2021 Halloween event)#1", "id": ["hist11235", "hist11256"], "page_name": "Brother Jered (2021 Halloween event)"}, {"page_name_sub": "Brother Jered (2021 Halloween event)#2", "id": ["hist11234"], "page_name": "Brother Jered (2021 Halloween event)"}, {"page_name_sub": "Barbarian (2021 Halloween event)", "id": ["hist11250"], "page_name": "Barbarian (2021 Halloween event)"}, {"page_name_sub": "Red partyhat (2013 April Fools)", "id": ["hist6205"], "page_name": "Red partyhat (2013 April Fools)"}, {"page_name_sub": "Yellow partyhat (2013 April Fools)", "id": ["hist6206"], "page_name": "Yellow partyhat (2013 April Fools)"}, {"page_name_sub": "Blue partyhat (2013 April Fools)", "id": ["hist6207"], "page_name": "Blue partyhat (2013 April Fools)"}, {"page_name_sub": "Green partyhat (2013 April Fools)", "id": ["hist6208"], "page_name": "Green partyhat (2013 April Fools)"}, {"page_name_sub": "Purple partyhat (2013 April Fools)", "id": ["hist6209"], "page_name": "Purple partyhat (2013 April Fools)"}, {"page_name_sub": "White partyhat (2013 April Fools)", "id": ["hist6210"], "page_name": "White partyhat (2013 April Fools)"}, {"page_name_sub": "Easter egg (2013 April Fools)", "id": ["hist6204"], "page_name": "Easter egg (2013 April Fools)"}, {"page_name_sub": "Gnome child (2013 Thanksgiving event)#Blue", "id": ["hist6530"], "page_name": "Gnome child (2013 Thanksgiving event)"}, {"page_name_sub": "Gnome child (2013 Thanksgiving event)#Yellow", "id": ["hist6529"], "page_name": "Gnome child (2013 Thanksgiving event)"}, {"page_name_sub": "Gnome (2013 Thanksgiving event)", "id": ["hist6531"], "page_name": "Gnome (2013 Thanksgiving event)"}, {"page_name_sub": "Spider (Hallowed Sepulchre)#1", "id": ["9643"], "page_name": "Spider (Hallowed Sepulchre)"}, {"page_name_sub": "Spider (Hallowed Sepulchre)#2", "id": ["9644"], "page_name": "Spider (Hallowed Sepulchre)"}, {"page_name_sub": "Bat (Hallowed Sepulchre)", "id": ["9641", "9642"], "page_name": "Bat (Hallowed Sepulchre)"}, {"page_name_sub": "Messenger (The Frozen Door)", "id": ["11287"], "page_name": "Messenger (The Frozen Door)"}, {"page_name_sub": "Blood Reaver#Ancient Prison", "id": ["11293"], "page_name": "Blood Reaver"}, {"page_name_sub": "Blood Reaver#Nex's chamber", "id": ["11294"], "page_name": "Blood Reaver"}, {"page_name_sub": "Buoy (2021 Christmas event)", "id": ["hist11241", "hist11243"], "page_name": "Buoy (2021 Christmas event)"}, {"page_name_sub": "Gurl", "id": ["hist11242", "hist11244"], "page_name": "Gurl"}, {"page_name_sub": "Ashuelot Reis", "id": ["11288", "11289"], "page_name": "Ashuelot Reis"}, {"page_name_sub": "Nexling", "id": ["11276", "11277"], "page_name": "Nexling"}, {"page_name_sub": "Snowball (2021 Christmas event)#Normal", "id": ["hist11236"], "page_name": "Snowball (2021 Christmas event)"}, {"page_name_sub": "Snowball (2021 Christmas event)#Mini", "id": ["hist11233"], "page_name": "Snowball (2021 Christmas event)"}, {"page_name_sub": "Snowball (2021 Christmas event)#Big", "id": ["hist11237"], "page_name": "Snowball (2021 Christmas event)"}, {"page_name_sub": "Snowball (2021 Christmas event)#Little", "id": ["hist11234"], "page_name": "Snowball (2021 Christmas event)"}, {"page_name_sub": "Snowball (2021 Christmas event)#Humongous", "id": ["hist11240"], "page_name": "Snowball (2021 Christmas event)"}, {"page_name_sub": "Snowball (2021 Christmas event)#Small", "id": ["hist11235"], "page_name": "Snowball (2021 Christmas event)"}, {"page_name_sub": "Snowball (2021 Christmas event)#Tiny", "id": ["hist11232"], "page_name": "Snowball (2021 Christmas event)"}, {"page_name_sub": "Snowball (2021 Christmas event)#Huge", "id": ["hist11239"], "page_name": "Snowball (2021 Christmas event)"}]}